{
"meta":{"test_sets":[],"test_metrics":[],"learn_metrics":[{"best_value":"Min","name":"RMSE"}],"launch_mode":"Train","parameters":"","iteration_count":1000,"learn_sets":["learn"],"name":"experiment"},
"iterations":[
{"learn":[14.61268541],"iteration":0,"passed_time":0.1717867977,"remaining_time":171.6150109},
{"learn":[14.23196558],"iteration":1,"passed_time":0.1725447711,"remaining_time":86.09984077},
{"learn":[13.86674177],"iteration":2,"passed_time":0.1732312528,"remaining_time":57.57051969},
{"learn":[13.49946468],"iteration":3,"passed_time":0.1740401446,"remaining_time":43.33599601},
{"learn":[13.16661202],"iteration":4,"passed_time":0.1748138797,"remaining_time":34.78796207},
{"learn":[12.85632158],"iteration":5,"passed_time":0.1756948159,"remaining_time":29.1067745},
{"learn":[12.56784336],"iteration":6,"passed_time":0.176274814,"remaining_time":25.00584148},
{"learn":[12.31617801],"iteration":7,"passed_time":0.1768783782,"remaining_time":21.9329189},
{"learn":[12.01509946],"iteration":8,"passed_time":0.177522123,"remaining_time":19.54715821},
{"learn":[11.71512571],"iteration":9,"passed_time":0.1781771202,"remaining_time":17.6395349},
{"learn":[11.43264457],"iteration":10,"passed_time":0.1788526233,"remaining_time":16.08047677},
{"learn":[11.17973129],"iteration":11,"passed_time":0.1795205209,"remaining_time":14.78052289},
{"learn":[10.93746433],"iteration":12,"passed_time":0.1801469882,"remaining_time":13.67731364},
{"learn":[10.69387075],"iteration":13,"passed_time":0.1807340652,"remaining_time":12.72884202},
{"learn":[10.4615922],"iteration":14,"passed_time":0.1813447892,"remaining_time":11.90830783},
{"learn":[10.2299235],"iteration":15,"passed_time":0.1822028864,"remaining_time":11.20547751},
{"learn":[10.01419731],"iteration":16,"passed_time":0.1827695244,"remaining_time":10.56837897},
{"learn":[9.795856918],"iteration":17,"passed_time":0.183327288,"remaining_time":10.00152204},
{"learn":[9.60040151],"iteration":18,"passed_time":0.1840144531,"remaining_time":9.50095676},
{"learn":[9.418664989],"iteration":19,"passed_time":0.1846898684,"remaining_time":9.049803552},
{"learn":[9.249278645],"iteration":20,"passed_time":0.1853371659,"remaining_time":8.640242162},
{"learn":[9.090113396],"iteration":21,"passed_time":0.1859609907,"remaining_time":8.266811314},
{"learn":[8.909548708],"iteration":22,"passed_time":0.1865293561,"remaining_time":7.92344265},
{"learn":[8.740140208],"iteration":23,"passed_time":0.187115131,"remaining_time":7.609348659},
{"learn":[8.59377682],"iteration":24,"passed_time":0.1877116996,"remaining_time":7.320756286},
{"learn":[8.453885414],"iteration":25,"passed_time":0.1882799416,"remaining_time":7.053256274},
{"learn":[8.317732234],"iteration":26,"passed_time":0.1888445139,"remaining_time":6.805396742},
{"learn":[8.180896085],"iteration":27,"passed_time":0.189404267,"remaining_time":6.575033841},
{"learn":[8.053220863],"iteration":28,"passed_time":0.1899703976,"remaining_time":6.360732968},
{"learn":[7.924234474],"iteration":29,"passed_time":0.1905169365,"remaining_time":6.160047612},
{"learn":[7.818879511],"iteration":30,"passed_time":0.1910763056,"remaining_time":5.972675488},
{"learn":[7.719346395],"iteration":31,"passed_time":0.1916025369,"remaining_time":5.795976741},
{"learn":[7.624163594],"iteration":32,"passed_time":0.1921759724,"remaining_time":5.631338343},
{"learn":[7.524952543],"iteration":33,"passed_time":0.1926978976,"remaining_time":5.474887325},
{"learn":[7.424464745],"iteration":34,"passed_time":0.1932665435,"remaining_time":5.3286347},
{"learn":[7.327482321],"iteration":35,"passed_time":0.1938613094,"remaining_time":5.191175064},
{"learn":[7.238666841],"iteration":36,"passed_time":0.1943941306,"remaining_time":5.059501292},
{"learn":[7.158842395],"iteration":37,"passed_time":0.1950526243,"remaining_time":4.937911174},
{"learn":[7.074348246],"iteration":38,"passed_time":0.1956746853,"remaining_time":4.821624937},
{"learn":[6.992269093],"iteration":39,"passed_time":0.1962271631,"remaining_time":4.709451915},
{"learn":[6.925219745],"iteration":40,"passed_time":0.1967485528,"remaining_time":4.601996638},
{"learn":[6.86013671],"iteration":41,"passed_time":0.1972932127,"remaining_time":4.500164233},
{"learn":[6.786739622],"iteration":42,"passed_time":0.1978242616,"remaining_time":4.402739962},
{"learn":[6.73057926],"iteration":43,"passed_time":0.1983872748,"remaining_time":4.310414425},
{"learn":[6.666356486],"iteration":44,"passed_time":0.1989705531,"remaining_time":4.222597293},
{"learn":[6.606182832],"iteration":45,"passed_time":0.1995286821,"remaining_time":4.138051364},
{"learn":[6.547854615],"iteration":46,"passed_time":0.2000595226,"remaining_time":4.056526065},
{"learn":[6.49240675],"iteration":47,"passed_time":0.2006435199,"remaining_time":3.979429811},
{"learn":[6.431317261],"iteration":48,"passed_time":0.2012043752,"remaining_time":3.905007364},
{"learn":[6.377586395],"iteration":49,"passed_time":0.2017686838,"remaining_time":3.833604992},
{"learn":[6.327558015],"iteration":50,"passed_time":0.2023018264,"remaining_time":3.764400652},
{"learn":[6.282040317],"iteration":51,"passed_time":0.2028241347,"remaining_time":3.697639994},
{"learn":[6.237655841],"iteration":52,"passed_time":0.203384271,"remaining_time":3.634054804},
{"learn":[6.192792003],"iteration":53,"passed_time":0.2039442942,"remaining_time":3.572801895},
{"learn":[6.150579347],"iteration":54,"passed_time":0.2044992209,"remaining_time":3.513668433},
{"learn":[6.115693845],"iteration":55,"passed_time":0.2050480692,"remaining_time":3.456524595},
{"learn":[6.078780782],"iteration":56,"passed_time":0.2056022328,"remaining_time":3.401454483},
{"learn":[6.045146957],"iteration":57,"passed_time":0.2061398644,"remaining_time":3.347995728},
{"learn":[6.008080327],"iteration":58,"passed_time":0.206714891,"remaining_time":3.29692733},
{"learn":[5.977575734],"iteration":59,"passed_time":0.2072268532,"remaining_time":3.246554033},
{"learn":[5.948036502],"iteration":60,"passed_time":0.2077756629,"remaining_time":3.198382746},
{"learn":[5.914888282],"iteration":61,"passed_time":0.2083616442,"remaining_time":3.152310036},
{"learn":[5.884957796],"iteration":62,"passed_time":0.2089456839,"remaining_time":3.107652474},
{"learn":[5.849539885],"iteration":63,"passed_time":0.2095609365,"remaining_time":3.064828697},
{"learn":[5.821387627],"iteration":64,"passed_time":0.2101372995,"remaining_time":3.022744231},
{"learn":[5.797012279],"iteration":65,"passed_time":0.2106672846,"remaining_time":2.98126127},
{"learn":[5.768685095],"iteration":66,"passed_time":0.2111893292,"remaining_time":2.940890211},
{"learn":[5.755484587],"iteration":67,"passed_time":0.2114928058,"remaining_time":2.898695515},
{"learn":[5.731887055],"iteration":68,"passed_time":0.2120557461,"remaining_time":2.861215936},
{"learn":[5.707148487],"iteration":69,"passed_time":0.2126107778,"remaining_time":2.824686048},
{"learn":[5.685365039],"iteration":70,"passed_time":0.2131733606,"remaining_time":2.789268338},
{"learn":[5.663541834],"iteration":71,"passed_time":0.2136962043,"remaining_time":2.754306634},
{"learn":[5.638108797],"iteration":72,"passed_time":0.2142541186,"remaining_time":2.720733807},
{"learn":[5.619204893],"iteration":73,"passed_time":0.2148025067,"remaining_time":2.687934071},
{"learn":[5.598472793],"iteration":74,"passed_time":0.2153276334,"remaining_time":2.655707479},
{"learn":[5.577007075],"iteration":75,"passed_time":0.2158862531,"remaining_time":2.62472234},
{"learn":[5.562637084],"iteration":76,"passed_time":0.2164049149,"remaining_time":2.594048526},
{"learn":[5.54729991],"iteration":77,"passed_time":0.2169434042,"remaining_time":2.564382291},
{"learn":[5.530737623],"iteration":78,"passed_time":0.2174620685,"remaining_time":2.535222343},
{"learn":[5.513704873],"iteration":79,"passed_time":0.2179790494,"remaining_time":2.506759068},
{"learn":[5.501575529],"iteration":80,"passed_time":0.2185035821,"remaining_time":2.479071506},
{"learn":[5.484080734],"iteration":81,"passed_time":0.2190583694,"remaining_time":2.452385159},
{"learn":[5.472178894],"iteration":82,"passed_time":0.2196464407,"remaining_time":2.426696219},
{"learn":[5.458923342],"iteration":83,"passed_time":0.2202294024,"remaining_time":2.401549197},
{"learn":[5.451382371],"iteration":84,"passed_time":0.2206059915,"remaining_time":2.374758615},
{"learn":[5.441410748],"iteration":85,"passed_time":0.2211409722,"remaining_time":2.350265681},
{"learn":[5.434047468],"iteration":86,"passed_time":0.2215147045,"remaining_time":2.324631324},
{"learn":[5.422107497],"iteration":87,"passed_time":0.2220815893,"remaining_time":2.301572835},
{"learn":[5.40731265],"iteration":88,"passed_time":0.2226410194,"remaining_time":2.278943468},
{"learn":[5.396360181],"iteration":89,"passed_time":0.2233665884,"remaining_time":2.258484394},
{"learn":[5.383793239],"iteration":90,"passed_time":0.224044847,"remaining_time":2.237986439},
{"learn":[5.369605034],"iteration":91,"passed_time":0.2246035084,"remaining_time":2.216738974},
{"learn":[5.357467333],"iteration":92,"passed_time":0.2251710594,"remaining_time":2.196023128},
{"learn":[5.341109968],"iteration":93,"passed_time":0.2257415691,"remaining_time":2.175764485},
{"learn":[5.330529276],"iteration":94,"passed_time":0.2262640641,"remaining_time":2.155462927},
{"learn":[5.319862075],"iteration":95,"passed_time":0.226792192,"remaining_time":2.135626475},
{"learn":[5.313052243],"iteration":96,"passed_time":0.2273476061,"remaining_time":2.116442148},
{"learn":[5.299677207],"iteration":97,"passed_time":0.2279014571,"remaining_time":2.097623615},
{"learn":[5.287546698],"iteration":98,"passed_time":0.2284703524,"remaining_time":2.079310985},
{"learn":[5.279803754],"iteration":99,"passed_time":0.2289910511,"remaining_time":2.06091946},
{"learn":[5.272254612],"iteration":100,"passed_time":0.2295472451,"remaining_time":2.043197756},
{"learn":[5.268813888],"iteration":101,"passed_time":0.2298556628,"remaining_time":2.023631227},
{"learn":[5.258113767],"iteration":102,"passed_time":0.2304175217,"remaining_time":2.006645796},
{"learn":[5.251018576],"iteration":103,"passed_time":0.230934586,"remaining_time":1.989590279},
{"learn":[5.24171237],"iteration":104,"passed_time":0.2315046019,"remaining_time":1.97330113},
{"learn":[5.233984943],"iteration":105,"passed_time":0.2320662924,"remaining_time":1.957238353},
{"learn":[5.226240449],"iteration":106,"passed_time":0.2325966688,"remaining_time":1.941203974},
{"learn":[5.220541644],"iteration":107,"passed_time":0.2331764353,"remaining_time":1.925864632},
{"learn":[5.211712096],"iteration":108,"passed_time":0.2337588542,"remaining_time":1.91081779},
{"learn":[5.203388597],"iteration":109,"passed_time":0.2343248165,"remaining_time":1.895900788},
{"learn":[5.196026544],"iteration":110,"passed_time":0.2348725994,"remaining_time":1.881096765},
{"learn":[5.188716772],"iteration":111,"passed_time":0.2353839684,"remaining_time":1.866258606},
{"learn":[5.182163132],"iteration":112,"passed_time":0.2359241153,"remaining_time":1.851899914},
{"learn":[5.17764747],"iteration":113,"passed_time":0.236430912,"remaining_time":1.837524456},
{"learn":[5.170548056],"iteration":114,"passed_time":0.2369315725,"remaining_time":1.823342971},
{"learn":[5.165901827],"iteration":115,"passed_time":0.2373970318,"remaining_time":1.809129105},
{"learn":[5.160333668],"iteration":116,"passed_time":0.2381411689,"remaining_time":1.797253437},
{"learn":[5.148953243],"iteration":117,"passed_time":0.2387540276,"remaining_time":1.784585189},
{"learn":[5.144729126],"iteration":118,"passed_time":0.2392677833,"remaining_time":1.771385858},
{"learn":[5.139939946],"iteration":119,"passed_time":0.2398769746,"remaining_time":1.759097814},
{"learn":[5.132898872],"iteration":120,"passed_time":0.2404511127,"remaining_time":1.746748166},
{"learn":[5.129073077],"iteration":121,"passed_time":0.2410605722,"remaining_time":1.734845757},
{"learn":[5.127123916],"iteration":122,"passed_time":0.2414073249,"remaining_time":1.721253853},
{"learn":[5.121282057],"iteration":123,"passed_time":0.2420401656,"remaining_time":1.709896654},
{"learn":[5.114489821],"iteration":124,"passed_time":0.2426619336,"remaining_time":1.698633535},
{"learn":[5.107777291],"iteration":125,"passed_time":0.2432236013,"remaining_time":1.687122441},
{"learn":[5.103518754],"iteration":126,"passed_time":0.2438846325,"remaining_time":1.676466804},
{"learn":[5.101133351],"iteration":127,"passed_time":0.2442592184,"remaining_time":1.664015925},
{"learn":[5.096462705],"iteration":128,"passed_time":0.2448820585,"remaining_time":1.653428472},
{"learn":[5.08562082],"iteration":129,"passed_time":0.2454182841,"remaining_time":1.64241467},
{"learn":[5.080483682],"iteration":130,"passed_time":0.2459410797,"remaining_time":1.631471743},
{"learn":[5.07437499],"iteration":131,"passed_time":0.2464551452,"remaining_time":1.620629288},
{"learn":[5.070683732],"iteration":132,"passed_time":0.2470459529,"remaining_time":1.610442415},
{"learn":[5.06432037],"iteration":133,"passed_time":0.2475683502,"remaining_time":1.599956651},
{"learn":[5.057436484],"iteration":134,"passed_time":0.2480796919,"remaining_time":1.589547655},
{"learn":[5.053254656],"iteration":135,"passed_time":0.2485983633,"remaining_time":1.579330779},
{"learn":[5.04801663],"iteration":136,"passed_time":0.2491586391,"remaining_time":1.569517559},
{"learn":[5.045680836],"iteration":137,"passed_time":0.2496415443,"remaining_time":1.559355154},
{"learn":[5.041857933],"iteration":138,"passed_time":0.2501780857,"remaining_time":1.549664257},
{"learn":[5.035264888],"iteration":139,"passed_time":0.2506987972,"remaining_time":1.540006897},
{"learn":[5.028771948],"iteration":140,"passed_time":0.2512477056,"remaining_time":1.530650916},
{"learn":[5.024912247],"iteration":141,"passed_time":0.2517935943,"remaining_time":1.521400732},
{"learn":[5.02239068],"iteration":142,"passed_time":0.2524460685,"remaining_time":1.512911054},
{"learn":[5.017110572],"iteration":143,"passed_time":0.2532404815,"remaining_time":1.505373974},
{"learn":[5.010707886],"iteration":144,"passed_time":0.2538507947,"remaining_time":1.496844341},
{"learn":[5.004389868],"iteration":145,"passed_time":0.2543816199,"remaining_time":1.487958243},
{"learn":[4.997628683],"iteration":146,"passed_time":0.25496056,"remaining_time":1.479465018},
{"learn":[4.991497851],"iteration":147,"passed_time":0.2555247291,"remaining_time":1.470993711},
{"learn":[4.988345253],"iteration":148,"passed_time":0.2560934456,"remaining_time":1.462654511},
{"learn":[4.98460423],"iteration":149,"passed_time":0.2566187647,"remaining_time":1.454173},
{"learn":[4.982441783],"iteration":150,"passed_time":0.2571442914,"remaining_time":1.445798036},
{"learn":[4.977461771],"iteration":151,"passed_time":0.2576674486,"remaining_time":1.437513134},
{"learn":[4.973601586],"iteration":152,"passed_time":0.2582340256,"remaining_time":1.429570064},
{"learn":[4.968328804],"iteration":153,"passed_time":0.2587473441,"remaining_time":1.421430215},
{"learn":[4.9640736],"iteration":154,"passed_time":0.2592688829,"remaining_time":1.413433587},
{"learn":[4.960865882],"iteration":155,"passed_time":0.2597788771,"remaining_time":1.405470335},
{"learn":[4.957014156],"iteration":156,"passed_time":0.260295745,"remaining_time":1.397638936},
{"learn":[4.952244852],"iteration":157,"passed_time":0.2608692723,"remaining_time":1.390202071},
{"learn":[4.949695675],"iteration":158,"passed_time":0.2614026329,"remaining_time":1.382639084},
{"learn":[4.946584698],"iteration":159,"passed_time":0.2619332001,"remaining_time":1.3751493},
{"learn":[4.940192834],"iteration":160,"passed_time":0.2625052079,"remaining_time":1.367961922},
{"learn":[4.936727994],"iteration":161,"passed_time":0.2630636817,"remaining_time":1.360786205},
{"learn":[4.932342063],"iteration":162,"passed_time":0.2636308696,"remaining_time":1.353736428},
{"learn":[4.925830838],"iteration":163,"passed_time":0.2641792537,"remaining_time":1.346669854},
{"learn":[4.922571773],"iteration":164,"passed_time":0.2647451262,"remaining_time":1.33977079},
{"learn":[4.918395814],"iteration":165,"passed_time":0.2653053081,"remaining_time":1.33291944},
{"learn":[4.911142452],"iteration":166,"passed_time":0.2658268621,"remaining_time":1.325950756},
{"learn":[4.908276131],"iteration":167,"passed_time":0.2663511311,"remaining_time":1.319072269},
{"learn":[4.904584645],"iteration":168,"passed_time":0.2669772477,"remaining_time":1.31276978},
{"learn":[4.89795517],"iteration":169,"passed_time":0.2677532674,"remaining_time":1.307265953},
{"learn":[4.895556491],"iteration":170,"passed_time":0.2683306115,"remaining_time":1.300854251},
{"learn":[4.890591233],"iteration":171,"passed_time":0.2688861218,"remaining_time":1.294405284},
{"learn":[4.884629277],"iteration":172,"passed_time":0.2694304113,"remaining_time":1.28797081},
{"learn":[4.880550786],"iteration":173,"passed_time":0.269938424,"remaining_time":1.281431829},
{"learn":[4.876384842],"iteration":174,"passed_time":0.2704569352,"remaining_time":1.275011266},
{"learn":[4.872638238],"iteration":175,"passed_time":0.270989362,"remaining_time":1.268722922},
{"learn":[4.869137118],"iteration":176,"passed_time":0.271539714,"remaining_time":1.262582964},
{"learn":[4.863587157],"iteration":177,"passed_time":0.2720527696,"remaining_time":1.256333576},
{"learn":[4.858028614],"iteration":178,"passed_time":0.2726146124,"remaining_time":1.250372049},
{"learn":[4.853838176],"iteration":179,"passed_time":0.273131627,"remaining_time":1.244266301},
{"learn":[4.853462329],"iteration":180,"passed_time":0.2734013566,"remaining_time":1.237103376},
{"learn":[4.851573196],"iteration":181,"passed_time":0.2739072074,"remaining_time":1.231077449},
{"learn":[4.848442087],"iteration":182,"passed_time":0.2744986238,"remaining_time":1.225493856},
{"learn":[4.845547104],"iteration":183,"passed_time":0.275052058,"remaining_time":1.219796083},
{"learn":[4.839868817],"iteration":184,"passed_time":0.2755723775,"remaining_time":1.214008042},
{"learn":[4.836336958],"iteration":185,"passed_time":0.2761358509,"remaining_time":1.208465498},
{"learn":[4.831124789],"iteration":186,"passed_time":0.2766850478,"remaining_time":1.202914138},
{"learn":[4.827407333],"iteration":187,"passed_time":0.277249269,"remaining_time":1.197480885},
{"learn":[4.824088918],"iteration":188,"passed_time":0.2777585217,"remaining_time":1.191863286},
{"learn":[4.820934539],"iteration":189,"passed_time":0.2782713376,"remaining_time":1.18631465},
{"learn":[4.816975227],"iteration":190,"passed_time":0.2787842985,"remaining_time":1.180819359},
{"learn":[4.812340486],"iteration":191,"passed_time":0.2793016377,"remaining_time":1.175394392},
{"learn":[4.806402747],"iteration":192,"passed_time":0.2798485157,"remaining_time":1.170143794},
{"learn":[4.801521788],"iteration":193,"passed_time":0.28036903,"remaining_time":1.164832156},
{"learn":[4.797601172],"iteration":194,"passed_time":0.280886867,"remaining_time":1.159558605},
{"learn":[4.792694629],"iteration":195,"passed_time":0.2814548052,"remaining_time":1.154539099},
{"learn":[4.789794613],"iteration":196,"passed_time":0.2822503461,"remaining_time":1.150492527},
{"learn":[4.785367055],"iteration":197,"passed_time":0.2828333638,"remaining_time":1.145617969},
{"learn":[4.780376856],"iteration":198,"passed_time":0.2834006415,"remaining_time":1.140723185},
{"learn":[4.776691261],"iteration":199,"passed_time":0.2839282195,"remaining_time":1.135712878},
{"learn":[4.773470753],"iteration":200,"passed_time":0.2844582046,"remaining_time":1.130756744},
{"learn":[4.77207327],"iteration":201,"passed_time":0.2850116853,"remaining_time":1.125937252},
{"learn":[4.767347177],"iteration":202,"passed_time":0.2855720428,"remaining_time":1.121186789},
{"learn":[4.763983068],"iteration":203,"passed_time":0.2860895808,"remaining_time":1.116310325},
{"learn":[4.761588849],"iteration":204,"passed_time":0.2866066804,"remaining_time":1.111474687},
{"learn":[4.758558086],"iteration":205,"passed_time":0.2871594484,"remaining_time":1.106818456},
{"learn":[4.753678804],"iteration":206,"passed_time":0.287680681,"remaining_time":1.102081063},
{"learn":[4.746510889],"iteration":207,"passed_time":0.2882517417,"remaining_time":1.09757394},
{"learn":[4.744840601],"iteration":208,"passed_time":0.2887866888,"remaining_time":1.092967803},
{"learn":[4.741702222],"iteration":209,"passed_time":0.2893246049,"remaining_time":1.088411609},
{"learn":[4.739352853],"iteration":210,"passed_time":0.2898481276,"remaining_time":1.083839681},
{"learn":[4.735539287],"iteration":211,"passed_time":0.2903718267,"remaining_time":1.079306601},
{"learn":[4.730726751],"iteration":212,"passed_time":0.2908875082,"remaining_time":1.074781544},
{"learn":[4.726416092],"iteration":213,"passed_time":0.2914130894,"remaining_time":1.070330319},
{"learn":[4.721293082],"iteration":214,"passed_time":0.2919723367,"remaining_time":1.066038532},
{"learn":[4.718443695],"iteration":215,"passed_time":0.292494924,"remaining_time":1.061648243},
{"learn":[4.711627962],"iteration":216,"passed_time":0.2930114223,"remaining_time":1.05727163},
{"learn":[4.709790764],"iteration":217,"passed_time":0.2935673671,"remaining_time":1.053071931},
{"learn":[4.706913073],"iteration":218,"passed_time":0.2941277775,"remaining_time":1.048921435},
{"learn":[4.703846389],"iteration":219,"passed_time":0.2946533427,"remaining_time":1.044680033},
{"learn":[4.701001135],"iteration":220,"passed_time":0.2951646066,"remaining_time":1.040421849},
{"learn":[4.700380864],"iteration":221,"passed_time":0.2956721296,"remaining_time":1.03618431},
{"learn":[4.695837486],"iteration":222,"passed_time":0.2961840172,"remaining_time":1.031995432},
{"learn":[4.691242996],"iteration":223,"passed_time":0.2968653194,"remaining_time":1.028426285},
{"learn":[4.690284609],"iteration":224,"passed_time":0.2974783492,"remaining_time":1.024647647},
{"learn":[4.68827119],"iteration":225,"passed_time":0.2981320891,"remaining_time":1.021036447},
{"learn":[4.686922425],"iteration":226,"passed_time":0.2987446752,"remaining_time":1.017311163},
{"learn":[4.686085874],"iteration":227,"passed_time":0.2993052323,"remaining_time":1.013437015},
{"learn":[4.683230741],"iteration":228,"passed_time":0.2999070382,"remaining_time":1.009730683},
{"learn":[4.6773487],"iteration":229,"passed_time":0.3005453903,"remaining_time":1.006173698},
{"learn":[4.671462906],"iteration":230,"passed_time":0.301132547,"remaining_time":1.002471553},
{"learn":[4.664799601],"iteration":231,"passed_time":0.3017667846,"remaining_time":0.9989521144},
{"learn":[4.660979386],"iteration":232,"passed_time":0.3023363804,"remaining_time":0.9952446514},
{"learn":[4.656281279],"iteration":233,"passed_time":0.3028723527,"remaining_time":0.9914539408},
{"learn":[4.651997094],"iteration":234,"passed_time":0.3034689979,"remaining_time":0.98788844},
{"learn":[4.650151977],"iteration":235,"passed_time":0.3040580007,"remaining_time":0.9843233583},
{"learn":[4.648478046],"iteration":236,"passed_time":0.3047093122,"remaining_time":0.9809839882},
{"learn":[4.646364602],"iteration":237,"passed_time":0.3052920442,"remaining_time":0.9774476372},
{"learn":[4.642635873],"iteration":238,"passed_time":0.3059668178,"remaining_time":0.9742290727},
{"learn":[4.640860821],"iteration":239,"passed_time":0.3065908763,"remaining_time":0.9708711084},
{"learn":[4.639446822],"iteration":240,"passed_time":0.3071022726,"remaining_time":0.9671810161},
{"learn":[4.637120072],"iteration":241,"passed_time":0.3076244775,"remaining_time":0.9635510492},
{"learn":[4.633769267],"iteration":242,"passed_time":0.3082198878,"remaining_time":0.9601747123},
{"learn":[4.630491517],"iteration":243,"passed_time":0.3088646082,"remaining_time":0.95697395},
{"learn":[4.627813333],"iteration":244,"passed_time":0.3094482909,"remaining_time":0.9536059575},
{"learn":[4.622496304],"iteration":245,"passed_time":0.3100008304,"remaining_time":0.9501651469},
{"learn":[4.618979301],"iteration":246,"passed_time":0.3105482863,"remaining_time":0.9467322251},
{"learn":[4.616563458],"iteration":247,"passed_time":0.3111073072,"remaining_time":0.9433576411},
{"learn":[4.614759385],"iteration":248,"passed_time":0.3117194692,"remaining_time":0.9401659494},
{"learn":[4.61251363],"iteration":249,"passed_time":0.3123115762,"remaining_time":0.9369347287},
{"learn":[4.608796693],"iteration":250,"passed_time":0.3128771305,"remaining_time":0.9336453017},
{"learn":[4.60847774],"iteration":251,"passed_time":0.3134089016,"remaining_time":0.9302772158},
{"learn":[4.605195659],"iteration":252,"passed_time":0.3140152585,"remaining_time":0.9271517712},
{"learn":[4.60103766],"iteration":253,"passed_time":0.3145988598,"remaining_time":0.9239793284},
{"learn":[4.599325598],"iteration":254,"passed_time":0.3152220846,"remaining_time":0.9209429532},
{"learn":[4.597012808],"iteration":255,"passed_time":0.3157781288,"remaining_time":0.9177301868},
{"learn":[4.594161533],"iteration":256,"passed_time":0.3163769644,"remaining_time":0.9146618075},
{"learn":[4.592197259],"iteration":257,"passed_time":0.3169388481,"remaining_time":0.9115062996},
{"learn":[4.58952828],"iteration":258,"passed_time":0.3174993146,"remaining_time":0.9083667651},
{"learn":[4.585816572],"iteration":259,"passed_time":0.3180742571,"remaining_time":0.9052882703},
{"learn":[4.582934052],"iteration":260,"passed_time":0.3186335942,"remaining_time":0.9021847745},
{"learn":[4.582234842],"iteration":261,"passed_time":0.3192346029,"remaining_time":0.89921808},
{"learn":[4.57571562],"iteration":262,"passed_time":0.319894661,"remaining_time":0.8964348484},
{"learn":[4.571197349],"iteration":263,"passed_time":0.3204458771,"remaining_time":0.8933642634},
{"learn":[4.56723703],"iteration":264,"passed_time":0.3210204749,"remaining_time":0.8903775436},
{"learn":[4.560335567],"iteration":265,"passed_time":0.3215604519,"remaining_time":0.8873134275},
{"learn":[4.554709345],"iteration":266,"passed_time":0.3220775747,"remaining_time":0.8842054767},
{"learn":[4.552806306],"iteration":267,"passed_time":0.3226561609,"remaining_time":0.8812847379},
{"learn":[4.550766241],"iteration":268,"passed_time":0.3231720468,"remaining_time":0.8782110268},
{"learn":[4.549216045],"iteration":269,"passed_time":0.32368512,"remaining_time":0.8751486577},
{"learn":[4.547687452],"iteration":270,"passed_time":0.3242313326,"remaining_time":0.8721942489},
{"learn":[4.545642435],"iteration":271,"passed_time":0.3247465107,"remaining_time":0.8691744845},
{"learn":[4.543930359],"iteration":272,"passed_time":0.3252520353,"remaining_time":0.8661473613},
{"learn":[4.541029943],"iteration":273,"passed_time":0.3257994699,"remaining_time":0.8632496903},
{"learn":[4.537781449],"iteration":274,"passed_time":0.326496491,"remaining_time":0.8607634762},
{"learn":[4.53066128],"iteration":275,"passed_time":0.327361574,"remaining_time":0.8587310855},
{"learn":[4.526763956],"iteration":276,"passed_time":0.3279818482,"remaining_time":0.8560681453},
{"learn":[4.522036004],"iteration":277,"passed_time":0.3285556196,"remaining_time":0.8532991271},
{"learn":[4.515307629],"iteration":278,"passed_time":0.3291273565,"remaining_time":0.850540588},
{"learn":[4.51109143],"iteration":279,"passed_time":0.3296589569,"remaining_time":0.8476944605},
{"learn":[4.508233494],"iteration":280,"passed_time":0.3301838936,"remaining_time":0.8448477562},
{"learn":[4.502555629],"iteration":281,"passed_time":0.3306979415,"remaining_time":0.8419897943},
{"learn":[4.500081355],"iteration":282,"passed_time":0.331215118,"remaining_time":0.8391563237},
{"learn":[4.495281743],"iteration":283,"passed_time":0.3317605899,"remaining_time":0.8364105014},
{"learn":[4.492138869],"iteration":284,"passed_time":0.33227715,"remaining_time":0.8336075869},
{"learn":[4.491708261],"iteration":285,"passed_time":0.3327813896,"remaining_time":0.8307899027},
{"learn":[4.489398865],"iteration":286,"passed_time":0.3332890087,"remaining_time":0.827996736},
{"learn":[4.485796373],"iteration":287,"passed_time":0.3338030791,"remaining_time":0.8252353899},
{"learn":[4.479542205],"iteration":288,"passed_time":0.3343265272,"remaining_time":0.8225126673},
{"learn":[4.475986993],"iteration":289,"passed_time":0.3348601757,"remaining_time":0.8198300853},
{"learn":[4.468661855],"iteration":290,"passed_time":0.3354046208,"remaining_time":0.8171885777},
{"learn":[4.463785664],"iteration":291,"passed_time":0.3359672997,"remaining_time":0.8146056445},
{"learn":[4.460445831],"iteration":292,"passed_time":0.3365277326,"remaining_time":0.8120310816},
{"learn":[4.45692492],"iteration":293,"passed_time":0.3370873931,"remaining_time":0.8094683657},
{"learn":[4.454031688],"iteration":294,"passed_time":0.3376105543,"remaining_time":0.8068320026},
{"learn":[4.451672391],"iteration":295,"passed_time":0.3381771634,"remaining_time":0.8043132535},
{"learn":[4.45031553],"iteration":296,"passed_time":0.3387055871,"remaining_time":0.801717265},
{"learn":[4.446782666],"iteration":297,"passed_time":0.3392670308,"remaining_time":0.7992129382},
{"learn":[4.444369689],"iteration":298,"passed_time":0.3398110815,"remaining_time":0.7966808298},
{"learn":[4.44411683],"iteration":299,"passed_time":0.3403129724,"remaining_time":0.7940636023},
{"learn":[4.440876943],"iteration":300,"passed_time":0.3409630302,"remaining_time":0.7918045119},
{"learn":[4.439336453],"iteration":301,"passed_time":0.3416727308,"remaining_time":0.7896939276},
{"learn":[4.436666901],"iteration":302,"passed_time":0.3422432141,"remaining_time":0.7872723439},
{"learn":[4.433043336],"iteration":303,"passed_time":0.3428794961,"remaining_time":0.7850135831},
{"learn":[4.431419305],"iteration":304,"passed_time":0.3435113188,"remaining_time":0.7827553002},
{"learn":[4.428859646],"iteration":305,"passed_time":0.3440941618,"remaining_time":0.780396563},
{"learn":[4.424552441],"iteration":306,"passed_time":0.344623254,"remaining_time":0.7779280619},
{"learn":[4.422706391],"iteration":307,"passed_time":0.3451392626,"remaining_time":0.7754427587},
{"learn":[4.421427994],"iteration":308,"passed_time":0.345647874,"remaining_time":0.7729536601},
{"learn":[4.418733158],"iteration":309,"passed_time":0.3461738512,"remaining_time":0.7705159915},
{"learn":[4.415656941],"iteration":310,"passed_time":0.3466939848,"remaining_time":0.7680776706},
{"learn":[4.410747417],"iteration":311,"passed_time":0.347220435,"remaining_time":0.7656655745},
{"learn":[4.408126521],"iteration":312,"passed_time":0.3477872333,"remaining_time":0.7633540871},
{"learn":[4.407843853],"iteration":313,"passed_time":0.3482873447,"remaining_time":0.7609080205},
{"learn":[4.405219398],"iteration":314,"passed_time":0.3488059208,"remaining_time":0.7585144626},
{"learn":[4.402708465],"iteration":315,"passed_time":0.3493225153,"remaining_time":0.7561284825},
{"learn":[4.40104971],"iteration":316,"passed_time":0.3498790524,"remaining_time":0.7538403559},
{"learn":[4.400830038],"iteration":317,"passed_time":0.35040041,"remaining_time":0.7514876719},
{"learn":[4.39784288],"iteration":318,"passed_time":0.3509934737,"remaining_time":0.7492995474},
{"learn":[4.393741845],"iteration":319,"passed_time":0.3515354844,"remaining_time":0.7470129044},
{"learn":[4.393425936],"iteration":320,"passed_time":0.352040447,"remaining_time":0.7446587649},
{"learn":[4.390505974],"iteration":321,"passed_time":0.3525572949,"remaining_time":0.7423411365},
{"learn":[4.390305136],"iteration":322,"passed_time":0.353083612,"remaining_time":0.7400545056},
{"learn":[4.38568203],"iteration":323,"passed_time":0.3536319817,"remaining_time":0.7378247519},
{"learn":[4.383057135],"iteration":324,"passed_time":0.3541910879,"remaining_time":0.7356276441},
{"learn":[4.380662684],"iteration":325,"passed_time":0.3547276629,"remaining_time":0.7333940025},
{"learn":[4.37805727],"iteration":326,"passed_time":0.3553352587,"remaining_time":0.7313169086},
{"learn":[4.373708319],"iteration":327,"passed_time":0.3560337555,"remaining_time":0.7294350114},
{"learn":[4.36887921],"iteration":328,"passed_time":0.3568758657,"remaining_time":0.7278532095},
{"learn":[4.367895929],"iteration":329,"passed_time":0.3575313042,"remaining_time":0.7258968903},
{"learn":[4.362140573],"iteration":330,"passed_time":0.3580726904,"remaining_time":0.7237179151},
{"learn":[4.361931924],"iteration":331,"passed_time":0.358605793,"remaining_time":0.7215321377},
{"learn":[4.359656377],"iteration":332,"passed_time":0.3591636471,"remaining_time":0.7194058637},
{"learn":[4.354281355],"iteration":333,"passed_time":0.3596804228,"remaining_time":0.7172070706},
{"learn":[4.348589447],"iteration":334,"passed_time":0.3602077779,"remaining_time":0.7150393204},
{"learn":[4.346355698],"iteration":335,"passed_time":0.3607268382,"remaining_time":0.7128649422},
{"learn":[4.343894047],"iteration":336,"passed_time":0.3612746484,"remaining_time":0.7107569492},
{"learn":[4.341561356],"iteration":337,"passed_time":0.3618530994,"remaining_time":0.7087182007},
{"learn":[4.338869061],"iteration":338,"passed_time":0.3623972255,"remaining_time":0.7066211388},
{"learn":[4.333720063],"iteration":339,"passed_time":0.3629288139,"remaining_time":0.704508874},
{"learn":[4.330892223],"iteration":340,"passed_time":0.3634948474,"remaining_time":0.7024724471},
{"learn":[4.328311474],"iteration":341,"passed_time":0.3640630005,"remaining_time":0.7004486968},
{"learn":[4.324580133],"iteration":342,"passed_time":0.3646945378,"remaining_time":0.6985548436},
{"learn":[4.323354432],"iteration":343,"passed_time":0.3652599694,"remaining_time":0.6965422672},
{"learn":[4.323159553],"iteration":344,"passed_time":0.3658498784,"remaining_time":0.6945845518},
{"learn":[4.318639682],"iteration":345,"passed_time":0.3664137902,"remaining_time":0.6925856035},
{"learn":[4.312712208],"iteration":346,"passed_time":0.3669884009,"remaining_time":0.6906150598},
{"learn":[4.311461062],"iteration":347,"passed_time":0.3675674595,"remaining_time":0.6886608725},
{"learn":[4.311178356],"iteration":348,"passed_time":0.3680842457,"remaining_time":0.6865984067},
{"learn":[4.311102505],"iteration":349,"passed_time":0.3686106052,"remaining_time":0.6845625526},
{"learn":[4.310232308],"iteration":350,"passed_time":0.3691560932,"remaining_time":0.682570668},
{"learn":[4.305128197],"iteration":351,"passed_time":0.3697658577,"remaining_time":0.6807053289},
{"learn":[4.304595496],"iteration":352,"passed_time":0.3704031216,"remaining_time":0.6788975062},
{"learn":[4.3004992],"iteration":353,"passed_time":0.3712303695,"remaining_time":0.6774429906},
{"learn":[4.297581524],"iteration":354,"passed_time":0.3719154893,"remaining_time":0.6757337764},
{"learn":[4.297355825],"iteration":355,"passed_time":0.3724700493,"remaining_time":0.6737941342},
{"learn":[4.295758715],"iteration":356,"passed_time":0.3730448371,"remaining_time":0.6718986842},
{"learn":[4.292500657],"iteration":357,"passed_time":0.3735992709,"remaining_time":0.6699741114},
{"learn":[4.290797586],"iteration":358,"passed_time":0.3741597811,"remaining_time":0.6680680213},
{"learn":[4.286410608],"iteration":359,"passed_time":0.3747197835,"remaining_time":0.666168504},
{"learn":[4.280278245],"iteration":360,"passed_time":0.3752463795,"remaining_time":0.6642172756},
{"learn":[4.279941283],"iteration":361,"passed_time":0.3757547329,"remaining_time":0.6622417668},
{"learn":[4.274426275],"iteration":362,"passed_time":0.3763179104,"remaining_time":0.660370548},
{"learn":[4.273567658],"iteration":363,"passed_time":0.3768292249,"remaining_time":0.6584158984},
{"learn":[4.269488271],"iteration":364,"passed_time":0.3774061381,"remaining_time":0.6565832813},
{"learn":[4.266838205],"iteration":365,"passed_time":0.3779374018,"remaining_time":0.6546784501},
{"learn":[4.263456509],"iteration":366,"passed_time":0.3784740017,"remaining_time":0.6527903081},
{"learn":[4.260360204],"iteration":367,"passed_time":0.3790388192,"remaining_time":0.6509579722},
{"learn":[4.255120549],"iteration":368,"passed_time":0.3795696565,"remaining_time":0.6490743991},
{"learn":[4.252582211],"iteration":369,"passed_time":0.3801199236,"remaining_time":0.6472312212},
{"learn":[4.247857931],"iteration":370,"passed_time":0.3806380107,"remaining_time":0.6453404548},
{"learn":[4.245288911],"iteration":371,"passed_time":0.38120232,"remaining_time":0.6435350994},
{"learn":[4.24048515],"iteration":372,"passed_time":0.3817509479,"remaining_time":0.6417100383},
{"learn":[4.2378365],"iteration":373,"passed_time":0.3822727888,"remaining_time":0.6398469674},
{"learn":[4.236751063],"iteration":374,"passed_time":0.3828020245,"remaining_time":0.6380033742},
{"learn":[4.233240093],"iteration":375,"passed_time":0.3833439526,"remaining_time":0.6361878362},
{"learn":[4.230358421],"iteration":376,"passed_time":0.3839045466,"remaining_time":0.6344099006},
{"learn":[4.225853583],"iteration":377,"passed_time":0.3844293815,"remaining_time":0.6325795643},
{"learn":[4.224702126],"iteration":378,"passed_time":0.3851263332,"remaining_time":0.6310381344},
{"learn":[4.224361982],"iteration":379,"passed_time":0.385989882,"remaining_time":0.6297729654},
{"learn":[4.223787954],"iteration":380,"passed_time":0.386518264,"remaining_time":0.6279653686},
{"learn":[4.22144054],"iteration":381,"passed_time":0.3870820259,"remaining_time":0.6262217068},
{"learn":[4.217739335],"iteration":382,"passed_time":0.3876533725,"remaining_time":0.6244964251},
{"learn":[4.215611665],"iteration":383,"passed_time":0.3882076868,"remaining_time":0.6227498308},
{"learn":[4.210236863],"iteration":384,"passed_time":0.3887429031,"remaining_time":0.6209789232},
{"learn":[4.208454294],"iteration":385,"passed_time":0.3892644347,"remaining_time":0.61919265},
{"learn":[4.207446501],"iteration":386,"passed_time":0.389774275,"remaining_time":0.6173943943},
{"learn":[4.204985442],"iteration":387,"passed_time":0.3903420585,"remaining_time":0.6156941747},
{"learn":[4.202796622],"iteration":388,"passed_time":0.3908973403,"remaining_time":0.6139801412},
{"learn":[4.199774004],"iteration":389,"passed_time":0.3914935479,"remaining_time":0.612336062},
{"learn":[4.199458358],"iteration":390,"passed_time":0.3920197038,"remaining_time":0.6105882343},
{"learn":[4.19751254],"iteration":391,"passed_time":0.3925735933,"remaining_time":0.6088896549},
{"learn":[4.195201346],"iteration":392,"passed_time":0.3931420926,"remaining_time":0.6072194661},
{"learn":[4.190593508],"iteration":393,"passed_time":0.3937409321,"remaining_time":0.6056015352},
{"learn":[4.187212054],"iteration":394,"passed_time":0.3943577595,"remaining_time":0.6040163151},
{"learn":[4.184984466],"iteration":395,"passed_time":0.3948918624,"remaining_time":0.6023098104},
{"learn":[4.182832144],"iteration":396,"passed_time":0.3954228055,"remaining_time":0.6006044124},
{"learn":[4.179752812],"iteration":397,"passed_time":0.3959712874,"remaining_time":0.5989314448},
{"learn":[4.17878934],"iteration":398,"passed_time":0.3964728104,"remaining_time":0.5971933811},
{"learn":[4.174548229],"iteration":399,"passed_time":0.3970132259,"remaining_time":0.5955198388},
{"learn":[4.168872556],"iteration":400,"passed_time":0.3975848642,"remaining_time":0.5938985877},
{"learn":[4.163926494],"iteration":401,"passed_time":0.3981352082,"remaining_time":0.5922508819},
{"learn":[4.159485076],"iteration":402,"passed_time":0.3986943104,"remaining_time":0.5906215964},
{"learn":[4.155926102],"iteration":403,"passed_time":0.399252579,"remaining_time":0.5889963789},
{"learn":[4.153540115],"iteration":404,"passed_time":0.3999727557,"remaining_time":0.5876142954},
{"learn":[4.150983044],"iteration":405,"passed_time":0.4006119715,"remaining_time":0.5861170224},
{"learn":[4.146539132],"iteration":406,"passed_time":0.4012062456,"remaining_time":0.5845584857},
{"learn":[4.144869174],"iteration":407,"passed_time":0.4017432191,"remaining_time":0.5829215336},
{"learn":[4.142825962],"iteration":408,"passed_time":0.4022871744,"remaining_time":0.5813000491},
{"learn":[4.142467378],"iteration":409,"passed_time":0.4027889828,"remaining_time":0.5796231703},
{"learn":[4.141800768],"iteration":410,"passed_time":0.4032964055,"remaining_time":0.5779600556},
{"learn":[4.140107084],"iteration":411,"passed_time":0.4038014587,"remaining_time":0.5762991692},
{"learn":[4.136243196],"iteration":412,"passed_time":0.4043869574,"remaining_time":0.5747582179},
{"learn":[4.133618439],"iteration":413,"passed_time":0.4049411859,"remaining_time":0.5731776207},
{"learn":[4.131053025],"iteration":414,"passed_time":0.4055028148,"remaining_time":0.5716124015},
{"learn":[4.128379975],"iteration":415,"passed_time":0.4061024768,"remaining_time":0.5701054001},
{"learn":[4.127068571],"iteration":416,"passed_time":0.4066603053,"remaining_time":0.5685442637},
{"learn":[4.125969877],"iteration":417,"passed_time":0.4071710795,"remaining_time":0.5669224121},
{"learn":[4.123893633],"iteration":418,"passed_time":0.4077212824,"remaining_time":0.5653605372},
{"learn":[4.119643722],"iteration":419,"passed_time":0.408289627,"remaining_time":0.5638285325},
{"learn":[4.11465686],"iteration":420,"passed_time":0.4088314501,"remaining_time":0.5622646308},
{"learn":[4.111565986],"iteration":421,"passed_time":0.409382247,"remaining_time":0.5607178643},
{"learn":[4.106322452],"iteration":422,"passed_time":0.4099440634,"remaining_time":0.5591908382},
{"learn":[4.104222175],"iteration":423,"passed_time":0.4104596431,"remaining_time":0.5576055529},
{"learn":[4.103008002],"iteration":424,"passed_time":0.410975307,"remaining_time":0.5560254154},
{"learn":[4.099176337],"iteration":425,"passed_time":0.4115223894,"remaining_time":0.5544926091},
{"learn":[4.096525716],"iteration":426,"passed_time":0.4120437205,"remaining_time":0.5529298638},
{"learn":[4.094967724],"iteration":427,"passed_time":0.4125658701,"remaining_time":0.5513730787},
{"learn":[4.094683584],"iteration":428,"passed_time":0.4130638316,"remaining_time":0.5497889228},
{"learn":[4.091096563],"iteration":429,"passed_time":0.4135728968,"remaining_time":0.5482245377},
{"learn":[4.089178677],"iteration":430,"passed_time":0.4141525868,"remaining_time":0.5467582874},
{"learn":[4.085335077],"iteration":431,"passed_time":0.4148120163,"remaining_time":0.5454009844},
{"learn":[4.084852122],"iteration":432,"passed_time":0.4154466599,"remaining_time":0.5440144484},
{"learn":[4.080322952],"iteration":433,"passed_time":0.4160253174,"remaining_time":0.5425583632},
{"learn":[4.077449519],"iteration":434,"passed_time":0.4165563374,"remaining_time":0.5410444382},
{"learn":[4.076568374],"iteration":435,"passed_time":0.4171040113,"remaining_time":0.539556565},
{"learn":[4.076071793],"iteration":436,"passed_time":0.4176080176,"remaining_time":0.5380167367},
{"learn":[4.075027644],"iteration":437,"passed_time":0.4181456139,"remaining_time":0.5365247375},
{"learn":[4.07020837],"iteration":438,"passed_time":0.4186666172,"remaining_time":0.5350158821},
{"learn":[4.06833694],"iteration":439,"passed_time":0.4192215175,"remaining_time":0.5335546586},
{"learn":[4.063936568],"iteration":440,"passed_time":0.419791765,"remaining_time":0.5321169992},
{"learn":[4.061734926],"iteration":441,"passed_time":0.420355167,"remaining_time":0.5306746226},
{"learn":[4.060815619],"iteration":442,"passed_time":0.420879727,"remaining_time":0.5291873768},
{"learn":[4.056407489],"iteration":443,"passed_time":0.421432075,"remaining_time":0.5277392651},
{"learn":[4.05238936],"iteration":444,"passed_time":0.4219781497,"remaining_time":0.5262873553},
{"learn":[4.049685254],"iteration":445,"passed_time":0.4224935739,"remaining_time":0.5248014349},
{"learn":[4.045162016],"iteration":446,"passed_time":0.4230225122,"remaining_time":0.5233365755},
{"learn":[4.042955482],"iteration":447,"passed_time":0.4235430771,"remaining_time":0.5218655771},
{"learn":[4.041467663],"iteration":448,"passed_time":0.4241036438,"remaining_time":0.5204479014},
{"learn":[4.038920476],"iteration":449,"passed_time":0.4246481546,"remaining_time":0.5190144112},
{"learn":[4.036694383],"iteration":450,"passed_time":0.4252074228,"remaining_time":0.5176028273},
{"learn":[4.034999007],"iteration":451,"passed_time":0.4257148359,"remaining_time":0.5161321461},
{"learn":[4.031928018],"iteration":452,"passed_time":0.4262638228,"remaining_time":0.5147159185},
{"learn":[4.028718143],"iteration":453,"passed_time":0.4268285786,"remaining_time":0.5133224756},
{"learn":[4.027401978],"iteration":454,"passed_time":0.4274304731,"remaining_time":0.5119771601},
{"learn":[4.025930598],"iteration":455,"passed_time":0.4279466861,"remaining_time":0.5105328887},
{"learn":[4.021074523],"iteration":456,"passed_time":0.4284885461,"remaining_time":0.5091231521},
{"learn":[4.020268486],"iteration":457,"passed_time":0.4290732728,"remaining_time":0.5077679342},
{"learn":[4.017986361],"iteration":458,"passed_time":0.4297119884,"remaining_time":0.5064797075},
{"learn":[4.014814804],"iteration":459,"passed_time":0.4302831097,"remaining_time":0.5051149549},
{"learn":[4.009704796],"iteration":460,"passed_time":0.4308839044,"remaining_time":0.5037883394},
{"learn":[4.008440457],"iteration":461,"passed_time":0.4314104587,"remaining_time":0.502378413},
{"learn":[4.004854849],"iteration":462,"passed_time":0.4319589839,"remaining_time":0.5009977848},
{"learn":[4.000898028],"iteration":463,"passed_time":0.4325061833,"remaining_time":0.4996192117},
{"learn":[3.996617985],"iteration":464,"passed_time":0.4330250039,"remaining_time":0.4982115636},
{"learn":[3.995443319],"iteration":465,"passed_time":0.4336372277,"remaining_time":0.496914763},
{"learn":[3.990771995],"iteration":466,"passed_time":0.4342627931,"remaining_time":0.4956361215},
{"learn":[3.989249359],"iteration":467,"passed_time":0.4348017818,"remaining_time":0.4942618545},
{"learn":[3.986599538],"iteration":468,"passed_time":0.4353883538,"remaining_time":0.4929450232},
{"learn":[3.985628919],"iteration":469,"passed_time":0.4359071159,"remaining_time":0.4915548328},
{"learn":[3.985086112],"iteration":470,"passed_time":0.4364130941,"remaining_time":0.4901539847},
{"learn":[3.98466839],"iteration":471,"passed_time":0.4370135152,"remaining_time":0.4888625764},
{"learn":[3.984233894],"iteration":472,"passed_time":0.4375120595,"remaining_time":0.4874605822},
{"learn":[3.981855845],"iteration":473,"passed_time":0.4380704924,"remaining_time":0.4861288587},
{"learn":[3.978684264],"iteration":474,"passed_time":0.4385939366,"remaining_time":0.4847617194},
{"learn":[3.974361269],"iteration":475,"passed_time":0.4391551975,"remaining_time":0.4834397552},
{"learn":[3.972074049],"iteration":476,"passed_time":0.4397218251,"remaining_time":0.4821268648},
{"learn":[3.97191982],"iteration":477,"passed_time":0.4402412597,"remaining_time":0.4807655597},
{"learn":[3.969616848],"iteration":478,"passed_time":0.4407906185,"remaining_time":0.4794403178},
{"learn":[3.968533527],"iteration":479,"passed_time":0.441335155,"remaining_time":0.4781130846},
{"learn":[3.967568753],"iteration":480,"passed_time":0.4418704731,"remaining_time":0.4767791592},
{"learn":[3.966232553],"iteration":481,"passed_time":0.4424230825,"remaining_time":0.4754671301},
{"learn":[3.961522393],"iteration":482,"passed_time":0.4429355568,"remaining_time":0.4741152855},
{"learn":[3.955829553],"iteration":483,"passed_time":0.4434919665,"remaining_time":0.4728137494},
{"learn":[3.954248095],"iteration":484,"passed_time":0.444113528,"remaining_time":0.4715844679},
{"learn":[3.951922606],"iteration":485,"passed_time":0.4447644303,"remaining_time":0.4703887184},
{"learn":[3.94978202],"iteration":486,"passed_time":0.4453461518,"remaining_time":0.4691223324},
{"learn":[3.949518999],"iteration":487,"passed_time":0.4459106291,"remaining_time":0.4678406601},
{"learn":[3.945431216],"iteration":488,"passed_time":0.4464963094,"remaining_time":0.4665840779},
{"learn":[3.943249086],"iteration":489,"passed_time":0.4470915498,"remaining_time":0.4653401845},
{"learn":[3.941981548],"iteration":490,"passed_time":0.4477016814,"remaining_time":0.4641143704},
{"learn":[3.936600517],"iteration":491,"passed_time":0.4482831765,"remaining_time":0.4628614912},
{"learn":[3.934476885],"iteration":492,"passed_time":0.4489218044,"remaining_time":0.4616700909},
{"learn":[3.93045798],"iteration":493,"passed_time":0.4495291545,"remaining_time":0.460448891},
{"learn":[3.925977375],"iteration":494,"passed_time":0.4501238402,"remaining_time":0.4592172511},
{"learn":[3.92457993],"iteration":495,"passed_time":0.4506669226,"remaining_time":0.4579357439},
{"learn":[3.919849146],"iteration":496,"passed_time":0.451228727,"remaining_time":0.4566761563},
{"learn":[3.919681964],"iteration":497,"passed_time":0.4517296544,"remaining_time":0.4553580051},
{"learn":[3.917633027],"iteration":498,"passed_time":0.4522459516,"remaining_time":0.4540585606},
{"learn":[3.916616419],"iteration":499,"passed_time":0.4527497559,"remaining_time":0.4527497559},
{"learn":[3.912896166],"iteration":500,"passed_time":0.4532795631,"remaining_time":0.4514700639},
{"learn":[3.912769674],"iteration":501,"passed_time":0.453771887,"remaining_time":0.4501561748},
{"learn":[3.909373788],"iteration":502,"passed_time":0.4542921336,"remaining_time":0.448873142},
{"learn":[3.906706036],"iteration":503,"passed_time":0.4548467349,"remaining_time":0.4476269455},
{"learn":[3.903895664],"iteration":504,"passed_time":0.4553640445,"remaining_time":0.4463469347},
{"learn":[3.902982967],"iteration":505,"passed_time":0.4558708019,"remaining_time":0.4450596366},
{"learn":[3.900905528],"iteration":506,"passed_time":0.4563912329,"remaining_time":0.4437887136},
{"learn":[3.897463465],"iteration":507,"passed_time":0.4569113536,"remaining_time":0.4425204448},
{"learn":[3.895918033],"iteration":508,"passed_time":0.4574572688,"remaining_time":0.441279998},
{"learn":[3.893921936],"iteration":509,"passed_time":0.4580278443,"remaining_time":0.440065968},
{"learn":[3.890237934],"iteration":510,"passed_time":0.4586546835,"remaining_time":0.4389082979},
{"learn":[3.887311613],"iteration":511,"passed_time":0.4592901266,"remaining_time":0.4377609019},
{"learn":[3.884869735],"iteration":512,"passed_time":0.4599685123,"remaining_time":0.436656268},
{"learn":[3.882101231],"iteration":513,"passed_time":0.4604941384,"remaining_time":0.4354088546},
{"learn":[3.88060368],"iteration":514,"passed_time":0.4610931286,"remaining_time":0.4342333347},
{"learn":[3.877726076],"iteration":515,"passed_time":0.4616689088,"remaining_time":0.4330382788},
{"learn":[3.874938145],"iteration":516,"passed_time":0.4622273048,"remaining_time":0.4318293776},
{"learn":[3.874340833],"iteration":517,"passed_time":0.4627386666,"remaining_time":0.4305792226},
{"learn":[3.873105224],"iteration":518,"passed_time":0.4632539361,"remaining_time":0.4293355361},
{"learn":[3.869800236],"iteration":519,"passed_time":0.4638255632,"remaining_time":0.4281466737},
{"learn":[3.867932518],"iteration":520,"passed_time":0.4643455749,"remaining_time":0.4269127263},
{"learn":[3.866666962],"iteration":521,"passed_time":0.4648749998,"remaining_time":0.4256901339},
{"learn":[3.865527652],"iteration":522,"passed_time":0.4654413195,"remaining_time":0.4245038421},
{"learn":[3.861900081],"iteration":523,"passed_time":0.4659678907,"remaining_time":0.4232838091},
{"learn":[3.858502887],"iteration":524,"passed_time":0.4664877293,"remaining_time":0.4220603265},
{"learn":[3.858335097],"iteration":525,"passed_time":0.4670170275,"remaining_time":0.4208480438},
{"learn":[3.855719306],"iteration":526,"passed_time":0.4675709258,"remaining_time":0.4196604324},
{"learn":[3.855137428],"iteration":527,"passed_time":0.4681251503,"remaining_time":0.4184755132},
{"learn":[3.851985706],"iteration":528,"passed_time":0.4686784747,"remaining_time":0.4172921769},
{"learn":[3.851051809],"iteration":529,"passed_time":0.4691960463,"remaining_time":0.4160795128},
{"learn":[3.850679146],"iteration":530,"passed_time":0.4696989329,"remaining_time":0.4148564963},
{"learn":[3.848179484],"iteration":531,"passed_time":0.4702035692,"remaining_time":0.4136377263},
{"learn":[3.844551071],"iteration":532,"passed_time":0.4707305917,"remaining_time":0.4124412502},
{"learn":[3.841604794],"iteration":533,"passed_time":0.4712447238,"remaining_time":0.4112360324},
{"learn":[3.83969656],"iteration":534,"passed_time":0.4717592687,"remaining_time":0.4100337569},
{"learn":[3.836811463],"iteration":535,"passed_time":0.4723126715,"remaining_time":0.4088676858},
{"learn":[3.834182551],"iteration":536,"passed_time":0.4728351233,"remaining_time":0.4076772106},
{"learn":[3.828012842],"iteration":537,"passed_time":0.4734903482,"remaining_time":0.4066032358},
{"learn":[3.826636176],"iteration":538,"passed_time":0.4741781321,"remaining_time":0.4055586621},
{"learn":[3.826189798],"iteration":539,"passed_time":0.4746868774,"remaining_time":0.4043628956},
{"learn":[3.824104738],"iteration":540,"passed_time":0.4752551804,"remaining_time":0.4032201992},
{"learn":[3.82300218],"iteration":541,"passed_time":0.4757722575,"remaining_time":0.4020363356},
{"learn":[3.817146402],"iteration":542,"passed_time":0.4763236636,"remaining_time":0.40088382},
{"learn":[3.814638044],"iteration":543,"passed_time":0.4768703772,"remaining_time":0.3997295809},
{"learn":[3.812979573],"iteration":544,"passed_time":0.4773928242,"remaining_time":0.3985573119},
{"learn":[3.811938825],"iteration":545,"passed_time":0.47790263,"remaining_time":0.3973769122},
{"learn":[3.811479418],"iteration":546,"passed_time":0.4784130299,"remaining_time":0.3961994562},
{"learn":[3.80742981],"iteration":547,"passed_time":0.4789593186,"remaining_time":0.3950540365},
{"learn":[3.805097043],"iteration":548,"passed_time":0.479490697,"remaining_time":0.3938985507},
{"learn":[3.801577232],"iteration":549,"passed_time":0.4800131407,"remaining_time":0.3927380242},
{"learn":[3.799762083],"iteration":550,"passed_time":0.480531583,"remaining_time":0.3915765531},
{"learn":[3.796393455],"iteration":551,"passed_time":0.4810943372,"remaining_time":0.3904533751},
{"learn":[3.793486459],"iteration":552,"passed_time":0.4816103498,"remaining_time":0.3892944419},
{"learn":[3.792006091],"iteration":553,"passed_time":0.4821698424,"remaining_time":0.3881728334},
{"learn":[3.78932128],"iteration":554,"passed_time":0.4827533179,"remaining_time":0.3870724801},
{"learn":[3.787581812],"iteration":555,"passed_time":0.4833683713,"remaining_time":0.385999203},
{"learn":[3.785308865],"iteration":556,"passed_time":0.4840167814,"remaining_time":0.3849541008},
{"learn":[3.78465475],"iteration":557,"passed_time":0.4846200906,"remaining_time":0.3838746954},
{"learn":[3.780498869],"iteration":558,"passed_time":0.4852239594,"remaining_time":0.3827974349},
{"learn":[3.778734909],"iteration":559,"passed_time":0.4858588009,"remaining_time":0.3817462007},
{"learn":[3.778652349],"iteration":560,"passed_time":0.4863619592,"remaining_time":0.3805934048},
{"learn":[3.777928006],"iteration":561,"passed_time":0.4868690284,"remaining_time":0.3794459688},
{"learn":[3.776131406],"iteration":562,"passed_time":0.4874479476,"remaining_time":0.3783565774},
{"learn":[3.772925617],"iteration":563,"passed_time":0.4880773976,"remaining_time":0.3773080592},
{"learn":[3.7727745],"iteration":564,"passed_time":0.4886397631,"remaining_time":0.3762093751},
{"learn":[3.771763073],"iteration":565,"passed_time":0.4892332625,"remaining_time":0.3751364592},
{"learn":[3.768738162],"iteration":566,"passed_time":0.48977588,"remaining_time":0.3740263775},
{"learn":[3.767220794],"iteration":567,"passed_time":0.4902884265,"remaining_time":0.3728954229},
{"learn":[3.766691102],"iteration":568,"passed_time":0.4908077857,"remaining_time":0.3717718025},
{"learn":[3.766259335],"iteration":569,"passed_time":0.4913187899,"remaining_time":0.3706439994},
{"learn":[3.76116362],"iteration":570,"passed_time":0.4918393027,"remaining_time":0.3695255006},
{"learn":[3.758633056],"iteration":571,"passed_time":0.4923541369,"remaining_time":0.3684048437},
{"learn":[3.754603809],"iteration":572,"passed_time":0.492927534,"remaining_time":0.3673299424},
{"learn":[3.754070549],"iteration":573,"passed_time":0.4934289784,"remaining_time":0.3662033882},
{"learn":[3.750534319],"iteration":574,"passed_time":0.4939921415,"remaining_time":0.3651246263},
{"learn":[3.746491516],"iteration":575,"passed_time":0.4945325963,"remaining_time":0.3640309389},
{"learn":[3.744210544],"iteration":576,"passed_time":0.495083693,"remaining_time":0.3629469708},
{"learn":[3.742929991],"iteration":577,"passed_time":0.4956071251,"remaining_time":0.3618446484},
{"learn":[3.740402992],"iteration":578,"passed_time":0.4961358301,"remaining_time":0.3607481597},
{"learn":[3.739644243],"iteration":579,"passed_time":0.4966894567,"remaining_time":0.3596716755},
{"learn":[3.737529404],"iteration":580,"passed_time":0.4972221905,"remaining_time":0.3585819239},
{"learn":[3.737196923],"iteration":581,"passed_time":0.4977440202,"remaining_time":0.3574862551},
{"learn":[3.733954464],"iteration":582,"passed_time":0.498306639,"remaining_time":0.3564217298},
{"learn":[3.731608623],"iteration":583,"passed_time":0.4988711432,"remaining_time":0.3553602664},
{"learn":[3.729843952],"iteration":584,"passed_time":0.4994435743,"remaining_time":0.3543061254},
{"learn":[3.727223798],"iteration":585,"passed_time":0.4999876924,"remaining_time":0.3532336257},
{"learn":[3.725351667],"iteration":586,"passed_time":0.5005332893,"remaining_time":0.3521639668},
{"learn":[3.725026912],"iteration":587,"passed_time":0.501077999,"remaining_time":0.3510954687},
{"learn":[3.721974565],"iteration":588,"passed_time":0.5016717236,"remaining_time":0.3500629514},
{"learn":[3.720269493],"iteration":589,"passed_time":0.502183309,"remaining_time":0.3489748418},
{"learn":[3.718907466],"iteration":590,"passed_time":0.5027187373,"remaining_time":0.3479051837},
{"learn":[3.715602912],"iteration":591,"passed_time":0.5032613484,"remaining_time":0.3468422807},
{"learn":[3.714463059],"iteration":592,"passed_time":0.5037625011,"remaining_time":0.3457526778},
{"learn":[3.710802077],"iteration":593,"passed_time":0.5043129212,"remaining_time":0.3446987307},
{"learn":[3.708032435],"iteration":594,"passed_time":0.5048563499,"remaining_time":0.3436417172},
{"learn":[3.703788939],"iteration":595,"passed_time":0.5054163146,"remaining_time":0.3425976361},
{"learn":[3.702500944],"iteration":596,"passed_time":0.5059308194,"remaining_time":0.3415244895},
{"learn":[3.698196925],"iteration":597,"passed_time":0.506481254,"remaining_time":0.3404773648},
{"learn":[3.69658891],"iteration":598,"passed_time":0.5069975953,"remaining_time":0.3394090746},
{"learn":[3.696124066],"iteration":599,"passed_time":0.5074992241,"remaining_time":0.3383328161},
{"learn":[3.693537052],"iteration":600,"passed_time":0.5080214514,"remaining_time":0.337272145},
{"learn":[3.691343275],"iteration":601,"passed_time":0.508537949,"remaining_time":0.3362094746},
{"learn":[3.690973831],"iteration":602,"passed_time":0.5090512025,"remaining_time":0.3351464799},
{"learn":[3.686151073],"iteration":603,"passed_time":0.5095838009,"remaining_time":0.3340979886},
{"learn":[3.683921982],"iteration":604,"passed_time":0.5101356511,"remaining_time":0.3330637722},
{"learn":[3.679975271],"iteration":605,"passed_time":0.5106768433,"remaining_time":0.3320242182},
{"learn":[3.674047638],"iteration":606,"passed_time":0.5112460296,"remaining_time":0.331004431},
{"learn":[3.673151794],"iteration":607,"passed_time":0.5117641968,"remaining_time":0.3299532322},
{"learn":[3.670953108],"iteration":608,"passed_time":0.5122779754,"remaining_time":0.3289009661},
{"learn":[3.6703947],"iteration":609,"passed_time":0.5128311795,"remaining_time":0.3278756721},
{"learn":[3.668433805],"iteration":610,"passed_time":0.513350275,"remaining_time":0.3268302078},
{"learn":[3.668304956],"iteration":611,"passed_time":0.5138517764,"remaining_time":0.3257753092},
{"learn":[3.667880012],"iteration":612,"passed_time":0.5143927842,"remaining_time":0.3247471574},
{"learn":[3.667282264],"iteration":613,"passed_time":0.5149350161,"remaining_time":0.3237213619},
{"learn":[3.664611483],"iteration":614,"passed_time":0.5155498844,"remaining_time":0.3227426105},
{"learn":[3.662543394],"iteration":615,"passed_time":0.5161219564,"remaining_time":0.3217383624},
{"learn":[3.659041959],"iteration":616,"passed_time":0.5166777344,"remaining_time":0.3207254007},
{"learn":[3.656868545],"iteration":617,"passed_time":0.5172042999,"remaining_time":0.3196958618},
{"learn":[3.654785614],"iteration":618,"passed_time":0.5177148809,"remaining_time":0.3186581093},
{"learn":[3.654566096],"iteration":619,"passed_time":0.5182217145,"remaining_time":0.3176197605},
{"learn":[3.651007045],"iteration":620,"passed_time":0.518782896,"remaining_time":0.3166162924},
{"learn":[3.648921786],"iteration":621,"passed_time":0.5193211584,"remaining_time":0.3156003182},
{"learn":[3.647655706],"iteration":622,"passed_time":0.5198303038,"remaining_time":0.3145682577},
{"learn":[3.647241144],"iteration":623,"passed_time":0.5203412054,"remaining_time":0.3135389315},
{"learn":[3.644195689],"iteration":624,"passed_time":0.5208506546,"remaining_time":0.3125103927},
{"learn":[3.642632246],"iteration":625,"passed_time":0.5214053577,"remaining_time":0.3115105491},
{"learn":[3.642523322],"iteration":626,"passed_time":0.521829971,"remaining_time":0.3104347356},
{"learn":[3.641494659],"iteration":627,"passed_time":0.522332395,"remaining_time":0.3094070875},
{"learn":[3.63976496],"iteration":628,"passed_time":0.5228378827,"remaining_time":0.3083829165},
{"learn":[3.637945652],"iteration":629,"passed_time":0.5233826092,"remaining_time":0.3073834371},
{"learn":[3.636233667],"iteration":630,"passed_time":0.5239260266,"remaining_time":0.3063846336},
{"learn":[3.635304404],"iteration":631,"passed_time":0.5244200732,"remaining_time":0.3053585236},
{"learn":[3.632234951],"iteration":632,"passed_time":0.524969707,"remaining_time":0.304366323},
{"learn":[3.631630987],"iteration":633,"passed_time":0.5254865933,"remaining_time":0.3033566138},
{"learn":[3.630301009],"iteration":634,"passed_time":0.5260288797,"remaining_time":0.3023630568},
{"learn":[3.629077964],"iteration":635,"passed_time":0.5265943185,"remaining_time":0.3013841697},
{"learn":[3.628004522],"iteration":636,"passed_time":0.5271066173,"remaining_time":0.3003762984},
{"learn":[3.625062876],"iteration":637,"passed_time":0.5276261569,"remaining_time":0.299374089},
{"learn":[3.624917986],"iteration":638,"passed_time":0.5281332879,"remaining_time":0.2983663802},
{"learn":[3.622887087],"iteration":639,"passed_time":0.5286496075,"remaining_time":0.2973654042},
{"learn":[3.621220865],"iteration":640,"passed_time":0.5291832102,"remaining_time":0.2963756201},
{"learn":[3.621143844],"iteration":641,"passed_time":0.529678969,"remaining_time":0.295366154},
{"learn":[3.620822821],"iteration":642,"passed_time":0.5301794988,"remaining_time":0.2943609348},
{"learn":[3.619202826],"iteration":643,"passed_time":0.5307164065,"remaining_time":0.2933773924},
{"learn":[3.618204882],"iteration":644,"passed_time":0.5312920023,"remaining_time":0.2924165284},
{"learn":[3.614259666],"iteration":645,"passed_time":0.5318578371,"remaining_time":0.2914515083},
{"learn":[3.613415661],"iteration":646,"passed_time":0.5323849317,"remaining_time":0.2904665856},
{"learn":[3.611096773],"iteration":647,"passed_time":0.5329027038,"remaining_time":0.2894780119},
{"learn":[3.610820695],"iteration":648,"passed_time":0.533405216,"remaining_time":0.2884826361},
{"learn":[3.609290065],"iteration":649,"passed_time":0.5339308813,"remaining_time":0.2875012438},
{"learn":[3.60897947],"iteration":650,"passed_time":0.5344341141,"remaining_time":0.2865092256},
{"learn":[3.606570702],"iteration":651,"passed_time":0.5349493989,"remaining_time":0.2855251393},
{"learn":[3.606292637],"iteration":652,"passed_time":0.5354579471,"remaining_time":0.2845389091},
{"learn":[3.602753838],"iteration":653,"passed_time":0.5359695445,"remaining_time":0.2835557529},
{"learn":[3.599755869],"iteration":654,"passed_time":0.5365311693,"remaining_time":0.2826003869},
{"learn":[3.599509575],"iteration":655,"passed_time":0.537045497,"remaining_time":0.2816214191},
{"learn":[3.595337722],"iteration":656,"passed_time":0.5375687263,"remaining_time":0.2806485131},
{"learn":[3.595168561],"iteration":657,"passed_time":0.5380647367,"remaining_time":0.2796628267},
{"learn":[3.59290559],"iteration":658,"passed_time":0.5386272489,"remaining_time":0.2787130378},
{"learn":[3.592015928],"iteration":659,"passed_time":0.5391372616,"remaining_time":0.2777373772},
{"learn":[3.590680403],"iteration":660,"passed_time":0.5396610529,"remaining_time":0.276770192},
{"learn":[3.590361532],"iteration":661,"passed_time":0.5401626175,"remaining_time":0.2757929981},
{"learn":[3.589069739],"iteration":662,"passed_time":0.5406789532,"remaining_time":0.2748247469},
{"learn":[3.585010186],"iteration":663,"passed_time":0.5412249357,"remaining_time":0.273872859},
{"learn":[3.582997552],"iteration":664,"passed_time":0.5417575365,"remaining_time":0.2729154507},
{"learn":[3.582119256],"iteration":665,"passed_time":0.5423075246,"remaining_time":0.2719680379},
{"learn":[3.579019356],"iteration":666,"passed_time":0.5428717963,"remaining_time":0.2710289478},
{"learn":[3.57719559],"iteration":667,"passed_time":0.5434005847,"remaining_time":0.2700733445},
{"learn":[3.574050046],"iteration":668,"passed_time":0.5439651722,"remaining_time":0.2691367294},
{"learn":[3.572204518],"iteration":669,"passed_time":0.5445232155,"remaining_time":0.2681980017},
{"learn":[3.569508025],"iteration":670,"passed_time":0.545082648,"remaining_time":0.2672610897},
{"learn":[3.566268704],"iteration":671,"passed_time":0.5456440171,"remaining_time":0.2663262464},
{"learn":[3.562564052],"iteration":672,"passed_time":0.5461986216,"remaining_time":0.2653892262},
{"learn":[3.561173586],"iteration":673,"passed_time":0.5467123023,"remaining_time":0.2644335468},
{"learn":[3.559551904],"iteration":674,"passed_time":0.5472754141,"remaining_time":0.2635029772},
{"learn":[3.558593054],"iteration":675,"passed_time":0.5478259682,"remaining_time":0.2625674759},
{"learn":[3.555647008],"iteration":676,"passed_time":0.5483938494,"remaining_time":0.2616413787},
{"learn":[3.553100059],"iteration":677,"passed_time":0.5489153746,"remaining_time":0.2606943224},
{"learn":[3.55085578],"iteration":678,"passed_time":0.5494677619,"remaining_time":0.2597631098},
{"learn":[3.550737965],"iteration":679,"passed_time":0.5499642517,"remaining_time":0.2588067067},
{"learn":[3.549408772],"iteration":680,"passed_time":0.5505329529,"remaining_time":0.2578854802},
{"learn":[3.547390589],"iteration":681,"passed_time":0.5510562793,"remaining_time":0.2569441302},
{"learn":[3.54723575],"iteration":682,"passed_time":0.5515632347,"remaining_time":0.2559964061},
{"learn":[3.543988891],"iteration":683,"passed_time":0.5520910363,"remaining_time":0.2550596016},
{"learn":[3.543868508],"iteration":684,"passed_time":0.5525936358,"remaining_time":0.2541124019},
{"learn":[3.542752124],"iteration":685,"passed_time":0.5531578394,"remaining_time":0.2531946962},
{"learn":[3.541334315],"iteration":686,"passed_time":0.5536742384,"remaining_time":0.2522562396},
{"learn":[3.540208266],"iteration":687,"passed_time":0.5541870911,"remaining_time":0.2513174018},
{"learn":[3.537730983],"iteration":688,"passed_time":0.5547101,"remaining_time":0.2503843847},
{"learn":[3.53419867],"iteration":689,"passed_time":0.5552835058,"remaining_time":0.2494751983},
{"learn":[3.532628335],"iteration":690,"passed_time":0.5557953541,"remaining_time":0.2485394565},
{"learn":[3.532204987],"iteration":691,"passed_time":0.5563625075,"remaining_time":0.2476295554},
{"learn":[3.530618147],"iteration":692,"passed_time":0.5568864062,"remaining_time":0.2467014815},
{"learn":[3.528909306],"iteration":693,"passed_time":0.557453328,"remaining_time":0.2457935423},
{"learn":[3.526700678],"iteration":694,"passed_time":0.5579814598,"remaining_time":0.2448695615},
{"learn":[3.526439574],"iteration":695,"passed_time":0.5584853115,"remaining_time":0.2439361131},
{"learn":[3.525784216],"iteration":696,"passed_time":0.5590008632,"remaining_time":0.2430089836},
{"learn":[3.524112693],"iteration":697,"passed_time":0.5595565209,"remaining_time":0.2421003858},
{"learn":[3.522813541],"iteration":698,"passed_time":0.5601050405,"remaining_time":0.2411897242},
{"learn":[3.519148203],"iteration":699,"passed_time":0.5606189762,"remaining_time":0.2402652755},
{"learn":[3.517236747],"iteration":700,"passed_time":0.5611424003,"remaining_time":0.2393460452},
{"learn":[3.515603888],"iteration":701,"passed_time":0.561711076,"remaining_time":0.2384471519},
{"learn":[3.51263524],"iteration":702,"passed_time":0.5622651434,"remaining_time":0.2375430264},
{"learn":[3.51123442],"iteration":703,"passed_time":0.5627927911,"remaining_time":0.2366287872},
{"learn":[3.50828027],"iteration":704,"passed_time":0.5633760188,"remaining_time":0.2357389015},
{"learn":[3.508265537],"iteration":705,"passed_time":0.5636976516,"remaining_time":0.2347409484},
{"learn":[3.506774876],"iteration":706,"passed_time":0.5642781539,"remaining_time":0.2338521911},
{"learn":[3.50552068],"iteration":707,"passed_time":0.5648108581,"remaining_time":0.2329445912},
{"learn":[3.501973993],"iteration":708,"passed_time":0.5653539749,"remaining_time":0.2320423226},
{"learn":[3.498880354],"iteration":709,"passed_time":0.5659124848,"remaining_time":0.2311473529},
{"learn":[3.497370959],"iteration":710,"passed_time":0.5664627518,"remaining_time":0.2302499793},
{"learn":[3.496050455],"iteration":711,"passed_time":0.5669685217,"remaining_time":0.2293355818},
{"learn":[3.495630067],"iteration":712,"passed_time":0.5674850537,"remaining_time":0.2284266626},
{"learn":[3.49550669],"iteration":713,"passed_time":0.5679953253,"remaining_time":0.2275163348},
{"learn":[3.493652375],"iteration":714,"passed_time":0.5685627224,"remaining_time":0.2266298963},
{"learn":[3.491915684],"iteration":715,"passed_time":0.5691151289,"remaining_time":0.2257384031},
{"learn":[3.490303956],"iteration":716,"passed_time":0.5696778263,"remaining_time":0.2248519175},
{"learn":[3.488363853],"iteration":717,"passed_time":0.5701986821,"remaining_time":0.2239499002},
{"learn":[3.485483936],"iteration":718,"passed_time":0.5707276372,"remaining_time":0.2230521086},
{"learn":[3.483763466],"iteration":719,"passed_time":0.5712928235,"remaining_time":0.2221694314},
{"learn":[3.481642352],"iteration":720,"passed_time":0.5718110253,"remaining_time":0.2212694536},
{"learn":[3.479826119],"iteration":721,"passed_time":0.5723539449,"remaining_time":0.2203800508},
{"learn":[3.478588728],"iteration":722,"passed_time":0.572887805,"remaining_time":0.2194881355},
{"learn":[3.475390887],"iteration":723,"passed_time":0.5734373674,"remaining_time":0.2186031953},
{"learn":[3.472636852],"iteration":724,"passed_time":0.5739895912,"remaining_time":0.2177201898},
{"learn":[3.47061883],"iteration":725,"passed_time":0.5745102258,"remaining_time":0.2168261734},
{"learn":[3.46953149],"iteration":726,"passed_time":0.5750236797,"remaining_time":0.2159304877},
{"learn":[3.467217162],"iteration":727,"passed_time":0.5755530444,"remaining_time":0.2150417968},
{"learn":[3.465686216],"iteration":728,"passed_time":0.576117668,"remaining_time":0.2141671989},
{"learn":[3.462631216],"iteration":729,"passed_time":0.5766827429,"remaining_time":0.2132936172},
{"learn":[3.461451053],"iteration":730,"passed_time":0.5771987026,"remaining_time":0.2124028057},
{"learn":[3.458950469],"iteration":731,"passed_time":0.5777585134,"remaining_time":0.2115290732},
{"learn":[3.458072145],"iteration":732,"passed_time":0.5783072783,"remaining_time":0.2106521737},
{"learn":[3.454364268],"iteration":733,"passed_time":0.5788303193,"remaining_time":0.2097668459},
{"learn":[3.453243406],"iteration":734,"passed_time":0.5793507518,"remaining_time":0.2088815636},
{"learn":[3.453017963],"iteration":735,"passed_time":0.5798564311,"remaining_time":0.2079919807},
{"learn":[3.45201581],"iteration":736,"passed_time":0.5803666321,"remaining_time":0.2071050533},
{"learn":[3.449510107],"iteration":737,"passed_time":0.5809079198,"remaining_time":0.2062301829},
{"learn":[3.447189189],"iteration":738,"passed_time":0.5814267812,"remaining_time":0.2053482949},
{"learn":[3.446423605],"iteration":739,"passed_time":0.5819822779,"remaining_time":0.2044802598},
{"learn":[3.445531987],"iteration":740,"passed_time":0.5825313041,"remaining_time":0.2036108067},
{"learn":[3.445328199],"iteration":741,"passed_time":0.5830325433,"remaining_time":0.2027256013},
{"learn":[3.443327544],"iteration":742,"passed_time":0.5835576395,"remaining_time":0.2018496815},
{"learn":[3.441475798],"iteration":743,"passed_time":0.5841583496,"remaining_time":0.2010007225},
{"learn":[3.439046501],"iteration":744,"passed_time":0.5847123834,"remaining_time":0.2001364534},
{"learn":[3.435899469],"iteration":745,"passed_time":0.5852566257,"remaining_time":0.1992696822},
{"learn":[3.433988352],"iteration":746,"passed_time":0.5858049088,"remaining_time":0.1984051431},
{"learn":[3.433413263],"iteration":747,"passed_time":0.5863219907,"remaining_time":0.1975309381},
{"learn":[3.429944699],"iteration":748,"passed_time":0.5868835458,"remaining_time":0.1966725901},
{"learn":[3.429291634],"iteration":749,"passed_time":0.5873944459,"remaining_time":0.1957981486},
{"learn":[3.429175603],"iteration":750,"passed_time":0.5879000361,"remaining_time":0.1949229148},
{"learn":[3.428780323],"iteration":751,"passed_time":0.5884039166,"remaining_time":0.1940481002},
{"learn":[3.423893341],"iteration":752,"passed_time":0.5889441373,"remaining_time":0.1931861911},
{"learn":[3.421024316],"iteration":753,"passed_time":0.5894656152,"remaining_time":0.1923190203},
{"learn":[3.420969872],"iteration":754,"passed_time":0.5899727197,"remaining_time":0.1914481011},
{"learn":[3.419544785],"iteration":755,"passed_time":0.5904864333,"remaining_time":0.1905802774},
{"learn":[3.417057977],"iteration":756,"passed_time":0.5910418281,"remaining_time":0.1897267691},
{"learn":[3.415160245],"iteration":757,"passed_time":0.5916009328,"remaining_time":0.1888752318},
{"learn":[3.412854597],"iteration":758,"passed_time":0.5921527942,"remaining_time":0.1880221652},
{"learn":[3.410926347],"iteration":759,"passed_time":0.5927134675,"remaining_time":0.187172674},
{"learn":[3.408963843],"iteration":760,"passed_time":0.5932897639,"remaining_time":0.1863288483},
{"learn":[3.407629634],"iteration":761,"passed_time":0.5938004932,"remaining_time":0.1854652459},
{"learn":[3.404384724],"iteration":762,"passed_time":0.594323115,"remaining_time":0.1846062624},
{"learn":[3.403041656],"iteration":763,"passed_time":0.5948459026,"remaining_time":0.1837482108},
{"learn":[3.401101731],"iteration":764,"passed_time":0.5953637629,"remaining_time":0.1828895219},
{"learn":[3.400890668],"iteration":765,"passed_time":0.5958790661,"remaining_time":0.1820309419},
{"learn":[3.399289941],"iteration":766,"passed_time":0.5964289099,"remaining_time":0.1811837497},
{"learn":[3.399202366],"iteration":767,"passed_time":0.596928873,"remaining_time":0.1803222637},
{"learn":[3.397447845],"iteration":768,"passed_time":0.5974940216,"remaining_time":0.1794812991},
{"learn":[3.394655341],"iteration":769,"passed_time":0.5980348764,"remaining_time":0.1786337942},
{"learn":[3.393228229],"iteration":770,"passed_time":0.5985471055,"remaining_time":0.1777785826},
{"learn":[3.389691197],"iteration":771,"passed_time":0.5990755299,"remaining_time":0.1769290425},
{"learn":[3.389626772],"iteration":772,"passed_time":0.5995774008,"remaining_time":0.1760725356},
{"learn":[3.388480222],"iteration":773,"passed_time":0.6000982863,"remaining_time":0.175222497},
{"learn":[3.388215066],"iteration":774,"passed_time":0.6006093747,"remaining_time":0.1743704636},
{"learn":[3.386324358],"iteration":775,"passed_time":0.6011377254,"remaining_time":0.1735242919},
{"learn":[3.383913061],"iteration":776,"passed_time":0.6016957815,"remaining_time":0.1726874637},
{"learn":[3.382839768],"iteration":777,"passed_time":0.6022534225,"remaining_time":0.1718512337},
{"learn":[3.381961844],"iteration":778,"passed_time":0.6028057729,"remaining_time":0.171014218},
{"learn":[3.381521703],"iteration":779,"passed_time":0.6033531558,"remaining_time":0.1701765311},
{"learn":[3.380918963],"iteration":780,"passed_time":0.6039645523,"remaining_time":0.1693575377},
{"learn":[3.377139006],"iteration":781,"passed_time":0.6044917167,"remaining_time":0.1685155937},
{"learn":[3.376004372],"iteration":782,"passed_time":0.605029127,"remaining_time":0.1676772932},
{"learn":[3.373826468],"iteration":783,"passed_time":0.6055606961,"remaining_time":0.166838151},
{"learn":[3.373546786],"iteration":784,"passed_time":0.6060814758,"remaining_time":0.1659968373},
{"learn":[3.372109181],"iteration":785,"passed_time":0.6066092437,"remaining_time":0.1651582419},
{"learn":[3.370764924],"iteration":786,"passed_time":0.6071647059,"remaining_time":0.1643279318},
{"learn":[3.367833107],"iteration":787,"passed_time":0.6076868491,"remaining_time":0.1634893553},
{"learn":[3.36450404],"iteration":788,"passed_time":0.6082502142,"remaining_time":0.1626626048},
{"learn":[3.361794558],"iteration":789,"passed_time":0.6088080603,"remaining_time":0.161835054},
{"learn":[3.356880529],"iteration":790,"passed_time":0.6093770109,"remaining_time":0.1610111192},
{"learn":[3.353843509],"iteration":791,"passed_time":0.6098928816,"remaining_time":0.1601738881},
{"learn":[3.353640253],"iteration":792,"passed_time":0.6104019676,"remaining_time":0.1593356965},
{"learn":[3.353055088],"iteration":793,"passed_time":0.6109171915,"remaining_time":0.1584999262},
{"learn":[3.351415617],"iteration":794,"passed_time":0.6114266623,"remaining_time":0.1576634789},
{"learn":[3.349169061],"iteration":795,"passed_time":0.6120488863,"remaining_time":0.1568567498},
{"learn":[3.346211014],"iteration":796,"passed_time":0.6127166176,"remaining_time":0.1560620745},
{"learn":[3.344560452],"iteration":797,"passed_time":0.6134551676,"remaining_time":0.1552856439},
{"learn":[3.344445461],"iteration":798,"passed_time":0.6140187499,"remaining_time":0.1544652925},
{"learn":[3.342608898],"iteration":799,"passed_time":0.614734279,"remaining_time":0.1536835697},
{"learn":[3.339572899],"iteration":800,"passed_time":0.6153624485,"remaining_time":0.1528803087},
{"learn":[3.339309302],"iteration":801,"passed_time":0.6159346291,"remaining_time":0.1520636615},
{"learn":[3.33698088],"iteration":802,"passed_time":0.6165678626,"remaining_time":0.1512626014},
{"learn":[3.334746342],"iteration":803,"passed_time":0.6172191159,"remaining_time":0.1504663516},
{"learn":[3.332048511],"iteration":804,"passed_time":0.6178090418,"remaining_time":0.1496556064},
{"learn":[3.331932544],"iteration":805,"passed_time":0.6183572331,"remaining_time":0.1488353638},
{"learn":[3.330541133],"iteration":806,"passed_time":0.6189129414,"remaining_time":0.1480175932},
{"learn":[3.329124989],"iteration":807,"passed_time":0.619469081,"remaining_time":0.1472005737},
{"learn":[3.32583918],"iteration":808,"passed_time":0.6200109449,"remaining_time":0.1463808288},
{"learn":[3.325287299],"iteration":809,"passed_time":0.620517356,"remaining_time":0.1455534539},
{"learn":[3.322745162],"iteration":810,"passed_time":0.6210748014,"remaining_time":0.1447387638},
{"learn":[3.319733662],"iteration":811,"passed_time":0.6216205635,"remaining_time":0.1439220024},
{"learn":[3.318080007],"iteration":812,"passed_time":0.6221438914,"remaining_time":0.1431007475},
{"learn":[3.317179538],"iteration":813,"passed_time":0.6226525341,"remaining_time":0.142276869},
{"learn":[3.315685949],"iteration":814,"passed_time":0.6232158063,"remaining_time":0.1414661646},
{"learn":[3.314944576],"iteration":815,"passed_time":0.6237368929,"remaining_time":0.1406465543},
{"learn":[3.312369052],"iteration":816,"passed_time":0.6243002636,"remaining_time":0.139837146},
{"learn":[3.312321621],"iteration":817,"passed_time":0.6246959275,"remaining_time":0.1389910254},
{"learn":[3.309465776],"iteration":818,"passed_time":0.6252185636,"remaining_time":0.138174066},
{"learn":[3.308307377],"iteration":819,"passed_time":0.6259050734,"remaining_time":0.1373937966},
{"learn":[3.308076804],"iteration":820,"passed_time":0.626440301,"remaining_time":0.1365807721},
{"learn":[3.305643326],"iteration":821,"passed_time":0.6269663247,"remaining_time":0.1357664304},
{"learn":[3.304154814],"iteration":822,"passed_time":0.6275108171,"remaining_time":0.1349567614},
{"learn":[3.303076321],"iteration":823,"passed_time":0.6280269459,"remaining_time":0.1341416778},
{"learn":[3.301746372],"iteration":824,"passed_time":0.6285847215,"remaining_time":0.133336153},
{"learn":[3.301345455],"iteration":825,"passed_time":0.6291350599,"remaining_time":0.1325296615},
{"learn":[3.299181039],"iteration":826,"passed_time":0.6296772413,"remaining_time":0.1317220831},
{"learn":[3.297989357],"iteration":827,"passed_time":0.6302332926,"remaining_time":0.130918027},
{"learn":[3.294775182],"iteration":828,"passed_time":0.6308032236,"remaining_time":0.1301174321},
{"learn":[3.293840636],"iteration":829,"passed_time":0.631313811,"remaining_time":0.1293052384},
{"learn":[3.289279397],"iteration":830,"passed_time":0.631885673,"remaining_time":0.1285062319},
{"learn":[3.286204979],"iteration":831,"passed_time":0.6325036867,"remaining_time":0.1277170906},
{"learn":[3.284833593],"iteration":832,"passed_time":0.6330556451,"remaining_time":0.1269151173},
{"learn":[3.283519914],"iteration":833,"passed_time":0.6336026352,"remaining_time":0.1261127547},
{"learn":[3.282853026],"iteration":834,"passed_time":0.6341272529,"remaining_time":0.1253065829},
{"learn":[3.281944673],"iteration":835,"passed_time":0.6346812586,"remaining_time":0.1245068498},
{"learn":[3.279764865],"iteration":836,"passed_time":0.6351925763,"remaining_time":0.1236993906},
{"learn":[3.277468839],"iteration":837,"passed_time":0.6357265887,"remaining_time":0.1228970255},
{"learn":[3.277124974],"iteration":838,"passed_time":0.6362430325,"remaining_time":0.1220919288},
{"learn":[3.275636037],"iteration":839,"passed_time":0.6367530548,"remaining_time":0.1212862962},
{"learn":[3.274413635],"iteration":840,"passed_time":0.6372639404,"remaining_time":0.1204815298},
{"learn":[3.272636087],"iteration":841,"passed_time":0.6377752789,"remaining_time":0.1196775464},
{"learn":[3.269644466],"iteration":842,"passed_time":0.6383467794,"remaining_time":0.1188854619},
{"learn":[3.26852083],"iteration":843,"passed_time":0.638895416,"remaining_time":0.118089674},
{"learn":[3.267820927],"iteration":844,"passed_time":0.6394669273,"remaining_time":0.1172986671},
{"learn":[3.267331099],"iteration":845,"passed_time":0.6400670322,"remaining_time":0.1165133841},
{"learn":[3.267231014],"iteration":846,"passed_time":0.6405887521,"remaining_time":0.1157143791},
{"learn":[3.267158695],"iteration":847,"passed_time":0.641085799,"remaining_time":0.1149116055},
{"learn":[3.264718705],"iteration":848,"passed_time":0.6415999928,"remaining_time":0.1141126018},
{"learn":[3.261678512],"iteration":849,"passed_time":0.6421274577,"remaining_time":0.1133166102},
{"learn":[3.261368381],"iteration":850,"passed_time":0.6426380291,"remaining_time":0.1125182918},
{"learn":[3.260128799],"iteration":851,"passed_time":0.6431561852,"remaining_time":0.1117219664},
{"learn":[3.258972952],"iteration":852,"passed_time":0.6437136762,"remaining_time":0.110933072},
{"learn":[3.258724846],"iteration":853,"passed_time":0.6442242339,"remaining_time":0.1101366957},
{"learn":[3.25686724],"iteration":854,"passed_time":0.644772901,"remaining_time":0.1093474511},
{"learn":[3.255750259],"iteration":855,"passed_time":0.6453282181,"remaining_time":0.1085598872},
{"learn":[3.254915866],"iteration":856,"passed_time":0.645900424,"remaining_time":0.1077756833},
{"learn":[3.254348625],"iteration":857,"passed_time":0.6464092896,"remaining_time":0.1069814908},
{"learn":[3.253408514],"iteration":858,"passed_time":0.6469279081,"remaining_time":0.1061895635},
{"learn":[3.253291714],"iteration":859,"passed_time":0.6474350655,"remaining_time":0.105396406},
{"learn":[3.250186342],"iteration":860,"passed_time":0.6479841422,"remaining_time":0.1046106803},
{"learn":[3.249141318],"iteration":861,"passed_time":0.6485522664,"remaining_time":0.1038285531},
{"learn":[3.246300388],"iteration":862,"passed_time":0.6491025551,"remaining_time":0.1030440904},
{"learn":[3.245205135],"iteration":863,"passed_time":0.6496250598,"remaining_time":0.1022557964},
{"learn":[3.244403535],"iteration":864,"passed_time":0.6501795549,"remaining_time":0.1014731097},
{"learn":[3.244211781],"iteration":865,"passed_time":0.6506879828,"remaining_time":0.1006838218},
{"learn":[3.242286347],"iteration":866,"passed_time":0.6512274348,"remaining_time":0.09989994097},
{"learn":[3.239606746],"iteration":867,"passed_time":0.6517400069,"remaining_time":0.09911253561},
{"learn":[3.236773361],"iteration":868,"passed_time":0.6522972975,"remaining_time":0.098332504},
{"learn":[3.234552446],"iteration":869,"passed_time":0.6528066288,"remaining_time":0.0975458181},
{"learn":[3.233724647],"iteration":870,"passed_time":0.6534154066,"remaining_time":0.09677449764},
{"learn":[3.230851485],"iteration":871,"passed_time":0.654023002,"remaining_time":0.09600337643},
{"learn":[3.227728941],"iteration":872,"passed_time":0.6545950283,"remaining_time":0.09522745543},
{"learn":[3.225787575],"iteration":873,"passed_time":0.6552802699,"remaining_time":0.09446832267},
{"learn":[3.222797487],"iteration":874,"passed_time":0.6558756623,"remaining_time":0.09369652318},
{"learn":[3.22137014],"iteration":875,"passed_time":0.6564582419,"remaining_time":0.09292331279},
{"learn":[3.219701963],"iteration":876,"passed_time":0.6570447514,"remaining_time":0.09215108828},
{"learn":[3.21783327],"iteration":877,"passed_time":0.6576327916,"remaining_time":0.09137949951},
{"learn":[3.217713355],"iteration":878,"passed_time":0.6581691594,"remaining_time":0.09060121534},
{"learn":[3.217666091],"iteration":879,"passed_time":0.6587341221,"remaining_time":0.08982738028},
{"learn":[3.214962005],"iteration":880,"passed_time":0.6593349027,"remaining_time":0.08905885746},
{"learn":[3.214081828],"iteration":881,"passed_time":0.6599076641,"remaining_time":0.08828696639},
{"learn":[3.213358337],"iteration":882,"passed_time":0.6604677082,"remaining_time":0.08751384128},
{"learn":[3.210850401],"iteration":883,"passed_time":0.6610005141,"remaining_time":0.08673762403},
{"learn":[3.207810328],"iteration":884,"passed_time":0.6615612307,"remaining_time":0.08596558366},
{"learn":[3.204935073],"iteration":885,"passed_time":0.6621935581,"remaining_time":0.08520323434},
{"learn":[3.20280198],"iteration":886,"passed_time":0.6628391422,"remaining_time":0.08444286704},
{"learn":[3.200663495],"iteration":887,"passed_time":0.6634933698,"remaining_time":0.08368384844},
{"learn":[3.197301669],"iteration":888,"passed_time":0.6640529385,"remaining_time":0.08291324655},
{"learn":[3.195666943],"iteration":889,"passed_time":0.6647487472,"remaining_time":0.08215995752},
{"learn":[3.193886506],"iteration":890,"passed_time":0.6654301797,"remaining_time":0.08140503882},
{"learn":[3.190601248],"iteration":891,"passed_time":0.6661439277,"remaining_time":0.08065419752},
{"learn":[3.188983797],"iteration":892,"passed_time":0.6668082894,"remaining_time":0.0798975218},
{"learn":[3.187365749],"iteration":893,"passed_time":0.6673771458,"remaining_time":0.0791297287},
{"learn":[3.186160771],"iteration":894,"passed_time":0.668031028,"remaining_time":0.07837235524},
{"learn":[3.185358981],"iteration":895,"passed_time":0.6686775203,"remaining_time":0.07761435503},
{"learn":[3.183832164],"iteration":896,"passed_time":0.6692779282,"remaining_time":0.07685131171},
{"learn":[3.183106966],"iteration":897,"passed_time":0.6698511865,"remaining_time":0.0760855468},
{"learn":[3.182838152],"iteration":898,"passed_time":0.6705378759,"remaining_time":0.0753329538},
{"learn":[3.180835453],"iteration":899,"passed_time":0.67109128,"remaining_time":0.07456569778},
{"learn":[3.179957348],"iteration":900,"passed_time":0.6716935476,"remaining_time":0.07380428547},
{"learn":[3.179752966],"iteration":901,"passed_time":0.6722923375,"remaining_time":0.07304284819},
{"learn":[3.178851983],"iteration":902,"passed_time":0.6728490778,"remaining_time":0.0722772542},
{"learn":[3.176748586],"iteration":903,"passed_time":0.6734951019,"remaining_time":0.07152160375},
{"learn":[3.172960988],"iteration":904,"passed_time":0.6741252253,"remaining_time":0.07076452641},
{"learn":[3.172794225],"iteration":905,"passed_time":0.6747735352,"remaining_time":0.07000961623},
{"learn":[3.169996507],"iteration":906,"passed_time":0.6754225865,"remaining_time":0.06925501714},
{"learn":[3.16813015],"iteration":907,"passed_time":0.6760739966,"remaining_time":0.06850088952},
{"learn":[3.166920871],"iteration":908,"passed_time":0.6766734774,"remaining_time":0.06774178927},
{"learn":[3.16531606],"iteration":909,"passed_time":0.6772893533,"remaining_time":0.06698466131},
{"learn":[3.162035247],"iteration":910,"passed_time":0.6778896951,"remaining_time":0.06622632586},
{"learn":[3.16189467],"iteration":911,"passed_time":0.678431842,"remaining_time":0.06546272159},
{"learn":[3.161008416],"iteration":912,"passed_time":0.6790897049,"remaining_time":0.06471062905},
{"learn":[3.160560787],"iteration":913,"passed_time":0.6798124891,"remaining_time":0.06396485127},
{"learn":[3.160416261],"iteration":914,"passed_time":0.6804992574,"remaining_time":0.06321577801},
{"learn":[3.15844291],"iteration":915,"passed_time":0.68114691,"remaining_time":0.06246325376},
{"learn":[3.155040501],"iteration":916,"passed_time":0.6817239795,"remaining_time":0.06170456958},
{"learn":[3.154937548],"iteration":917,"passed_time":0.6822985056,"remaining_time":0.06094605388},
{"learn":[3.153721161],"iteration":918,"passed_time":0.6828859137,"remaining_time":0.060189074},
{"learn":[3.153170511],"iteration":919,"passed_time":0.6834258875,"remaining_time":0.05942833804},
{"learn":[3.153113601],"iteration":920,"passed_time":0.6839740616,"remaining_time":0.05866878487},
{"learn":[3.150607379],"iteration":921,"passed_time":0.6845005887,"remaining_time":0.05790785891},
{"learn":[3.148408359],"iteration":922,"passed_time":0.6850818509,"remaining_time":0.05715200707},
{"learn":[3.147495728],"iteration":923,"passed_time":0.6856663284,"remaining_time":0.05639679757},
{"learn":[3.146946235],"iteration":924,"passed_time":0.6862382328,"remaining_time":0.0556409378},
{"learn":[3.14472738],"iteration":925,"passed_time":0.6868025639,"remaining_time":0.05488487011},
{"learn":[3.144469477],"iteration":926,"passed_time":0.6873816802,"remaining_time":0.05413038043},
{"learn":[3.142975516],"iteration":927,"passed_time":0.6879507567,"remaining_time":0.05337548974},
{"learn":[3.14079113],"iteration":928,"passed_time":0.688526302,"remaining_time":0.05262149348},
{"learn":[3.138173032],"iteration":929,"passed_time":0.6890732024,"remaining_time":0.05186572491},
{"learn":[3.136352813],"iteration":930,"passed_time":0.6896704993,"remaining_time":0.05111414012},
{"learn":[3.133735004],"iteration":931,"passed_time":0.690255325,"remaining_time":0.0503619765},
{"learn":[3.1319496],"iteration":932,"passed_time":0.6908636899,"remaining_time":0.04961186198},
{"learn":[3.129865343],"iteration":933,"passed_time":0.6915367061,"remaining_time":0.04886661949},
{"learn":[3.129830206],"iteration":934,"passed_time":0.6920891868,"remaining_time":0.04811315202},
{"learn":[3.126676562],"iteration":935,"passed_time":0.6927868676,"remaining_time":0.04737004223},
{"learn":[3.12645665],"iteration":936,"passed_time":0.6934387137,"remaining_time":0.04662394766},
{"learn":[3.126378007],"iteration":937,"passed_time":0.6940092883,"remaining_time":0.04587268217},
{"learn":[3.124621914],"iteration":938,"passed_time":0.6947222939,"remaining_time":0.04513105424},
{"learn":[3.123379018],"iteration":939,"passed_time":0.695307872,"remaining_time":0.04438135353},
{"learn":[3.123332451],"iteration":940,"passed_time":0.6959744421,"remaining_time":0.04363707979},
{"learn":[3.122432444],"iteration":941,"passed_time":0.6965671528,"remaining_time":0.04288842342},
{"learn":[3.121889006],"iteration":942,"passed_time":0.697238486,"remaining_time":0.04214485016},
{"learn":[3.121070914],"iteration":943,"passed_time":0.6978976899,"remaining_time":0.04140071042},
{"learn":[3.118444705],"iteration":944,"passed_time":0.6985445265,"remaining_time":0.04065603064},
{"learn":[3.116820458],"iteration":945,"passed_time":0.6991542321,"remaining_time":0.03990943819},
{"learn":[3.114971041],"iteration":946,"passed_time":0.6998090096,"remaining_time":0.03916565735},
{"learn":[3.114685138],"iteration":947,"passed_time":0.7004205011,"remaining_time":0.03841968994},
{"learn":[3.113399363],"iteration":948,"passed_time":0.7011086426,"remaining_time":0.03767812515},
{"learn":[3.110575399],"iteration":949,"passed_time":0.7017549729,"remaining_time":0.03693447226},
{"learn":[3.110466553],"iteration":950,"passed_time":0.7022980481,"remaining_time":0.03618570385},
{"learn":[3.108691641],"iteration":951,"passed_time":0.7029471852,"remaining_time":0.03544271522},
{"learn":[3.107898017],"iteration":952,"passed_time":0.7035946695,"remaining_time":0.03469984204},
{"learn":[3.105551729],"iteration":953,"passed_time":0.7041861172,"remaining_time":0.03395446687},
{"learn":[3.104824945],"iteration":954,"passed_time":0.7047823416,"remaining_time":0.03320963913},
{"learn":[3.103186704],"iteration":955,"passed_time":0.7053293141,"remaining_time":0.03246285546},
{"learn":[3.102330655],"iteration":956,"passed_time":0.7060449778,"remaining_time":0.03172406901},
{"learn":[3.102291298],"iteration":957,"passed_time":0.7066218389,"remaining_time":0.03097924555},
{"learn":[3.100363529],"iteration":958,"passed_time":0.707177128,"remaining_time":0.0302338501},
{"learn":[3.097871596],"iteration":959,"passed_time":0.7078495197,"remaining_time":0.02949372999},
{"learn":[3.097372213],"iteration":960,"passed_time":0.7084535877,"remaining_time":0.02875097806},
{"learn":[3.095981813],"iteration":961,"passed_time":0.7090334736,"remaining_time":0.02800755925},
{"learn":[3.095347452],"iteration":962,"passed_time":0.7096139828,"remaining_time":0.02726450401},
{"learn":[3.094728409],"iteration":963,"passed_time":0.7101648638,"remaining_time":0.02652067956},
{"learn":[3.094118537],"iteration":964,"passed_time":0.7107133281,"remaining_time":0.02577716734},
{"learn":[3.093793695],"iteration":965,"passed_time":0.7112202226,"remaining_time":0.02503259583},
{"learn":[3.092581602],"iteration":966,"passed_time":0.7117430543,"remaining_time":0.02428905977},
{"learn":[3.091694202],"iteration":967,"passed_time":0.712309605,"remaining_time":0.02354742496},
{"learn":[3.090298312],"iteration":968,"passed_time":0.7128670567,"remaining_time":0.02280586043},
{"learn":[3.090020107],"iteration":969,"passed_time":0.7133780321,"remaining_time":0.02206323811},
{"learn":[3.088949869],"iteration":970,"passed_time":0.7139005183,"remaining_time":0.0213214367},
{"learn":[3.086700204],"iteration":971,"passed_time":0.7144730376,"remaining_time":0.02058152783},
{"learn":[3.086584317],"iteration":972,"passed_time":0.7149867288,"remaining_time":0.0198403306},
{"learn":[3.084850742],"iteration":973,"passed_time":0.7155433798,"remaining_time":0.0191007473},
{"learn":[3.084239948],"iteration":974,"passed_time":0.7160998704,"remaining_time":0.01836153514},
{"learn":[3.082561673],"iteration":975,"passed_time":0.7166374563,"remaining_time":0.01762223253},
{"learn":[3.07991814],"iteration":976,"passed_time":0.7171988927,"remaining_time":0.01688390433},
{"learn":[3.079350277],"iteration":977,"passed_time":0.7177119875,"remaining_time":0.01614485043},
{"learn":[3.077637462],"iteration":978,"passed_time":0.7182625463,"remaining_time":0.01540706177},
{"learn":[3.076733301],"iteration":979,"passed_time":0.7187854863,"remaining_time":0.01466909156},
{"learn":[3.07594065],"iteration":980,"passed_time":0.719316039,"remaining_time":0.01393170718},
{"learn":[3.072594655],"iteration":981,"passed_time":0.7198751653,"remaining_time":0.0131952678},
{"learn":[3.071977674],"iteration":982,"passed_time":0.7204014374,"remaining_time":0.01245862099},
{"learn":[3.069532634],"iteration":983,"passed_time":0.7210051555,"remaining_time":0.01172366107},
{"learn":[3.068870784],"iteration":984,"passed_time":0.7216175023,"remaining_time":0.01098909902},
{"learn":[3.068801463],"iteration":985,"passed_time":0.7221912922,"remaining_time":0.01025423741},
{"learn":[3.067433249],"iteration":986,"passed_time":0.7227214296,"remaining_time":0.009519127239},
{"learn":[3.065611456],"iteration":987,"passed_time":0.7232427095,"remaining_time":0.008784324407},
{"learn":[3.063039162],"iteration":988,"passed_time":0.7237636238,"remaining_time":0.008049949304},
{"learn":[3.06177873],"iteration":989,"passed_time":0.7243396657,"remaining_time":0.00731656228},
{"learn":[3.061689148],"iteration":990,"passed_time":0.7248554931,"remaining_time":0.006582945952},
{"learn":[3.058984039],"iteration":991,"passed_time":0.7254111116,"remaining_time":0.00585008961},
{"learn":[3.057492984],"iteration":992,"passed_time":0.725933981,"remaining_time":0.005117359383},
{"learn":[3.057290731],"iteration":993,"passed_time":0.7264488353,"remaining_time":0.00438500303},
{"learn":[3.056068348],"iteration":994,"passed_time":0.7269550541,"remaining_time":0.003653040473},
{"learn":[3.054987307],"iteration":995,"passed_time":0.7274984571,"remaining_time":0.002921680551},
{"learn":[3.054200234],"iteration":996,"passed_time":0.7280205866,"remaining_time":0.002190633661},
{"learn":[3.052732869],"iteration":997,"passed_time":0.7285560771,"remaining_time":0.001460032219},
{"learn":[3.051787862],"iteration":998,"passed_time":0.7290955403,"remaining_time":0.0007298253657},
{"learn":[3.051366222],"iteration":999,"passed_time":0.7296077077,"remaining_time":0}
]}